Workbook
Name Accounts_payable: 'List Data'!$C$61:$F$61
Name Cash___Bank: 'List Data'!$C$24:$F$24
Name Debt: 'List Data'!$C$55:$F$55
Name Equity: 'List Data'!$C$49:$F$49
Name Fixed_Assets: 'List Data'!$C$17:$F$17
Name Inventory: 'List Data'!$C$39:$F$39
Name Loans___advances: 'List Data'!$C$73:$F$73
Name Manufacturing: 'List Data'!$C$4:$C$90
Name Operating_Expenses: 'List Data'!$C$90:$F$90
Name Payroll: 'List Data'!$C$30:$F$30
Name Receivables: 'List Data'!$C$46:$F$46
Name Revenue: 'List Data'!$C$84:$F$84
Name Service: 'List Data'!$E$4:$E$90
Name Trading: 'List Data'!$D$4:$D$90
Name Works_Contract: 'List Data'!$F$4:$F$90

Sheet Pending works on each acc bal
A2: Category | B2: Activity | C2: Status
A3: Cash | B3: SPCB5 - If physical verification of cash cannot be conducted at the balance sheet date, perform surprise verifcation of cash during the course of field audit work and obtain confirmation from the management with respect to cash balance as on the balance sheet date | C3: To be done
A4: Receivables | B4: CARE4 - The sale value is calculated and invoice is generated automatically by the application system. Sale prices are obtained from a master file. | C4: Control testing to be done
A5: Receivables | B5: CADRS6 - Write off of bad debts is done only after taking necessry approval from the senior management after recording the reasons for writing off the debtors as bad. | C5: Control testing to be done
A6: Inventory | B6: CAINV1 - Periodic counts of inventory is performed and reconciled to the stock register / general ledger. | C6: Control testing to be done
A7: Loans and Advances | B7: CALA4 - Advances/loans to staff are made as per the entity's policy for staff advances and loans after taking appropriate approvals and receipts are obtained from the staff where they acknowledge the receipt of the loan/advance | C7: Control testing to be done
A8: Accounts Payable | B8: CACL3 - Management reviews and approves payments before processing. | C8: Control testing to be done
A9: Revenue | B9: CARE2 - Invoices are sequentially numbered by the application system and the sequence of invoices processed is accounted for. | C9: Control testing to be done
A10: Revenue | B10: CARE5 - Access to the sales price master file is restricted to authorised personnel only. | C10: Control testing to be done

Sheet NET of FAP
B2: George Infra Private Limited
B3: Statutory Audit for the year ended 31.03.2020
B6: Control Activities | G6: Expected Man hours
B7: Account Balance | C7: Control Activity | D7: Test of control | E7: WP Reference | F7: Required Resource | G7: Min | H7: Max | I7: Avg | J7: Rate | K7: Cost | L7: Remarks
B8: Cash & Bank | C8: CACB1 - Cash on hand is physically verified and agreed with cash book periodically by the management. | D8: 1) Obtain details of physical verification of fixed assets performed by the entity and check if the periodicity of verification is appropriate | F8: Linson Francis | G8: 1 | H8: 1 | I8: =+AVERAGE(G8,H8) -> 1
B9: Cash & Bank | C9: CACB2 - Bank statements are periodically obtained and bank reconciliation statements are prepared every month and are reviewed and approved by the management | D9: 1) Obtain monthly bank reconciliation statements prepared by the entity and check whether the same are approved by the management | F9: Linson Francis | G9: 1 | H9: 1 | I9: =+AVERAGE(G9,H9) -> 1 | L9: 12 samples among all the bank a/cs spread over 12 months
B10: Cash & Bank | C10: CACB3 - Confirmation of bank balances at the balance sheet date for all accounts are obtained by the entity; the scanned copies of which are made available to the auditors. | D10: 1) Obtain bank confirmation statements | F10: Linson Francis | L10: Covered Under SPCB2
B11: Cash & Bank | C11: CACB4 - Bank Accounts are opened and closed with the approval of the Board of Directors. | D11: 1) Obtain minutes of the BoD meetings | F11: Linson Francis | G11: 0.5 | H11: 0.5 | I11: =+AVERAGE(G11,H11) -> 0.5
B12: Cash & Bank | C12: CACB5 - Cash balance is kept under lock & key so as to ensure there is no embezzlement or misappropriation | D12: 1) Check whether Cash is kept under lock & key and the authority for holding the key | F12: Linson Francis
B13: Payroll | C13: CAPAY2 - Biometric attendance systems installed at the office and factory premises ensure that employee attendance data is correctly captured before processing payroll | D13: 1) Obtain reports from the attendance system for a few samples covering the period under audit and check whether the attendance data is correctly captured for processing payroll | F13: Linson Francis | G13: 10 | H13: 14 | I13: =+AVERAGE(G13,H13) -> 12
B14: Inventory | C14: CAINV1 - Periodic counts of inventory is performed and reconciled to the stock register / general ledger. | D14: 1) Obtain details of physical verification of fixed assets performed by the entity and check if the periodicity of verification is appropriate
B15: Receivables | C15: CADRS6 - Write off of bad debts is done only after taking necessry approval from the senior management after recording the reasons for writing off the debtors as bad. | D15: 1) Obtain management approvals for write off of debts | F15: Linson Francis
B16: Accounts Payable | C16: CACL3 - Management reviews and approves payments before processing. | D16: 1) Obtain a few samples for payments processed during the year and check whether the payment is approved by the appropriate authority and whether there are adequate supportings
B17: Loans & Advances | C17: CALA4 - Advances/loans to staff are made as per the entity's policy for staff advances and loans after taking appropriate approvals and receipts are obtained from the staff where they acknowledge the receipt of the loan/advance | D17: 1) Obtain samples of a few staff loans/advances made during the year and compare the same with the entity's policy to see whether the same has been adherred to
B18: Revenue | C18: CARE2 - Invoices are sequentially numbered by the application system and the sequence of invoices processed is accounted for. | D18: 1) Test the sequential numbering of invoices in the system and see whether the same can be bypassed
B19: Revenue | C19: CARE4 - The sale value is calculated and invoice is generated automatically by the application system. Sale prices are obtained from a master file. | D19: 1) Select sample invoices and ensure that the sale prices and discounts given therein are as per the management approved pricelist and discount chart
B20: Revenue | C20: CARE5 - Access to the sales price master file is restricted to authorised personnel only. | D20: 1) Check who has the authority to alter the price master file in the system and whether the same can be bypassed
B21: Revenue | C21: CARE6 - The discount value shown on the invoice is calculated based on the management approved discount rates. | D21: 1) Obtain the management's discount policy and check in respect of a few samples whether the policy has been adherred to
B22: Operating Expenses | C22: CAEXP1 - Invoices and supporting documents are approved by the management before recording in the general ledger. | D22: 1) Obtain a few sample invoices and check whether the same have been authorised by the appropriate authority before recording the same in the general ledger
B25: Substantive procedures | G25: Expected Man hours
B26: Account Balance | C26: Substantive Procedure | D26: Description of Substantive procedure | E26: WP Reference | F26: Required Resource | G26: Min | H26: Max | I26: Avg | J26: Rate | K26: Cost | L26: Remarks
B27: Fixed Assets | C27: SPFA1 - Ensure that the opening balance of Fixed assets have been correctly carried forward from previous reporting period | D27: 1) Obtain opening trial balance of the financial year and compare the same with the closing audited trial balance of the previous year to ensure that the opening balances have been correctly carried forward | F27: Linson Francis | G27: 1 | H27: 3 | I27: =+AVERAGE(G27,H27) -> 2
B28: Fixed Assets | C28: SPFA2 - Obtain a list of Fixed Asset additions during the period and compare the amounts booked in the ledger with the relevant supporting documents. Ensure that all additions during the year have been correctly booked in the respective ledger accounts. | D28: 1) Obtain supportings for the fixed assets purchased during the year and ensure that the amounts are correctly accounted in the books. Check the classification of the additions made and ensure that all necessary compliances with the statutory framework as well as other legal frameworks are met | F28: Linson Francis | G28: 28 | H28: 40 | I28: =+AVERAGE(G28,H28) -> 34
B29: Fixed Assets | C29: SPFA3 - Obtain the records of the physical verification procedures carried out by the entity during the year. Alternatively, we may choose to visit a few locations on our own and physically verfiy the assets. | D29: 1) Obtain details of physical verification of fixed assets performed by the entity and check if the periodicity of verification is appropriate | F29: Linson Francis | G29: 1 | H29: 1 | I29: =+AVERAGE(G29,H29) -> 1 | L29: Already covered under Control testing
B30: Fixed Assets | C30: SPFA4 - Obtain a list of Asset Disposals during the year and ensure that the related amounts have been correctly removed from the Gross Block as well as Accumulated Depreciation | D30: 1) Scrutinise the fixed asset ledgers as well as the cash and bank books to find out any asset disposals during the year. Ensure that the related amounts upto the date of disposal are removed from gross block and accumulated depreciation | F30: Linson Francis | G30: 6 | H30: 10 | I30: =+AVERAGE(G30,H30) -> 8
B31: Fixed Assets | C31: SPFA5 - Obtain the rates of Deprecation for each category of assets as per the Companies Act as well as the Income Tax act and compute the Depreciation Expense for the year as per Companies Act and income Tax Act. | D31: 1) In respect of asset additions during the year, check whether the classification as per companies act and income tax act are proper. Ensure that the useful lives as well as rates of depeciation as given in the statutes are correctly captured 2) Periodically, review the classification of Fixed assets present in the opening block as well to confirm that the classification made earlier still remains appropriate | F31: Linson Francis | G31: 18 | H31: 24 | I31: =+AVERAGE(G31,H31) -> 21
B32: Fixed Assets | C32: SPFA6 - Review the Repairs and maintanence ledger to ensure that no asset which has to be capitalised has been wrongly expensed off | D32: 1) Scrutinise the repairs and maintenance ledger to identify any expenses that meets capitalisation criteria and therefore needs to be capitalised as fixed asset in the books of account | F32: Linson Francis | G32: 14 | H32: 18 | I32: =+AVERAGE(G32,H32) -> 16
B33: Fixed Assets | C33: SPFA7 - Perform test for impairment of fixed assets by evaluating the conditions for impairment as laid down in the applicable financial reporting framework | D33: 1) Perform impairment testing for fixed assets based on the conditions laid out in the financial reporting framework in the event of any fixed asset becoming obsolete/non usable | F33: Govind P | G33: 1 | H33: 3 | I33: =+AVERAGE(G33,H33) -> 2
B34: Cash & Bank | C34: SPCB1 - Perform physical verification of Cash on Hand at the balance sheet date | D34: 1) Visit the location where cash is physically maintained and physically verifiy the same in the presence of the authorised person from the entity's behalf 2) Note down the number of currencies in each denomination and check the physical cash balance with the balance as per the books of account | L34: Couldn't perform due to COVID lockdown
B35: Cash & Bank | C35: SPCB2 - Obtain bank reconciliation statements from the entity for all accounts (including zero balance accounts) and agree the bank book balance to the general ledger and the pass book balance to the bank statement. Trace the reconciling items to the bank statement for the subsequent period or general ledger as the case may be | D35: 1) Match the bank book balance to the general ledger 2) Match the pass book balance to the bank confirmation/statement 3) Trace the subsequent clearance of the reconciling items to the subsequent bank statement. 4) Where the items are not subsequently cleared, check if the instruments have become stale and if any reversal entry needs to be passed | G35: 10 | H35: 14 | I35: =+AVERAGE(G35,H35) -> 12
B36: Cash & Bank | C36: SPCB3 - Obtain balance confirmations for all bank accounts maintained by the entity. | D36: 1) Obtain balance confirmation statements directly from the bank 2) If direct confirmations are not available, have the entity obtain confirmations and communicate the same to the auditors | L36: Covered Under SPCB2
B37: Cash & Bank | C37: SPCB4 - Obtain minutes of Board of directors meeting conducted for the purpose of opening or closing bank accounts | D37: 1) Obtain minutes of BoD meetings and review the same | L37: Covered Under CACB4
B38: Cash & Bank | C38: SPCB5 - If physical verification of cash cannot be conducted at the balance sheet date, perform surprise verifcation of cash during the course of field audit work and obtain confirmation from the management with respect to cash balance as on the balance sheet date | D38: 1) Perform surprise verification of cash on a random date during field audit and compare the physical balance with the book balance 2) Obtain a confirmation from the entity regarding the physical cash balance as on the balance sheet date | G38: 0.5 | H38: 1.5 | I38: =+AVERAGE(G38,H38) -> 1
B39: Payroll | C39: SPPAY1 - Compare monthly payroll data maintained by the HR department with the amounts booked in the respective ledger accounts. Ensure that the net salary after LOP is booked as expense and statutory deductions are booked in the respective liability accounts | D39: 1) Check the payroll computations for each month after considering the base salary and the LOP days. Ensure that the calculations are correct and the correct amount is poseted in the ledger 2) Check if there are reconciling items between the payroll workings and the ledger balance such as amount paid to contract staff and such others who are not in payroll. Check if the grouping of such amounts as salary is appropriate | G39: 130 | H39: 150 | I39: =78+7+16+39 -> 140 | N39: Linson | O39: 78
B40: Payroll | C40: SPPAY2 - Independantly recalculate statutory deductions such as ESI, PF, EWF and compare with the amounts booked in the ledger. Ensure that there are no material differences. | D40: 1) Recalculate statutory deductions based on the rates as given in the statute and ensure that there are no short deductions or material differences | N40: Robin | O40: 7
B41: Payroll | C41: SPPAY3 - Check incentive computation and esnure that the same is consistent through out the period and appropriately accounted | D41: 1) If incentives are paid to the staff, check the parameters for incentive computation and ensure that the incentive is computed appropriately. 2) Also whether statutory deductions are correctly made wherever applocable | N41: Rahul M (Pkd) | O41: 16
B42: Payroll | C42: SPPAY4 - Check the wages/salary payable balance as at the balance sheet date and obtain employeewise, monthwise breakup of the same to identify if there are any long outstanding balances that are no longer payable | D42: 1) Obtain monthwise employeewise split up of the balance in wages payable ledger 2) Check if there are any amounts which are no longer payable and need to be written back 3) Check subsequent settlement of the salary payable balance
B43: Payroll | C43: SPPAY5 - Check the base data given to the actuary for actuarial valuation and ensure that there are no inconsistencies | D43: 1) Compare the salary given for actuarial valuation with the monthly payroll data 2) Trace other data such as joining date, leave data on a sample basis with the employee personnel files, leave cards or such other records | F43: Linson Francis | G43: 6 | H43: 10 | I43: =+AVERAGE(G43,H43) -> 8
B44: Inventory | C44: SPINV1 - Identify significant locations of inventory including third party locations and perform test counts of stock on the balance sheet date | D44: 1) Enquire with the management regarding significant locations of inventory. Visit such locations during the entity's inventory verification process. Observe the enitity's inventory count process and perform test counts on a sample basis
B45: Inventory | C45: SPINV2 - Incase of inventories owned by the entity but located at third party premises, obtain confirmation from the third parties as to the stock in hand as on the balance sheet date. | D45: 1) Visit 3rd party locations where inventory is kept by the entity and perform test counts. 2) If unable to visit, request confirmations for the inventory held by the 3rd parties
B46: Inventory | C46: SPINV3 - Ensure that inventories are measured at lower of cost or NRV and that a recogonised cost formula as per AS 2 is used for valuation. Also ensure that all associated costs incurred in bringing the inventories to their present location and condition are taken while valuing inventories | D46: 1) Check whether all costrs related to bring the inventory to its present location and condition as required by the FRF are considered for inventory valuation 2) On a sample basis, perform Cost NRV comparison to ensure that inventory is not stated over its recoverable value
B47: Receivables | C47: SPDRS1 - Obtain the list of Debtors/ Debtors Trial Balance from the accounting package and agree the total with the balance as per general ledger. Obtain/Calculate the ageing of Debtors based on Invoice date. Perform subsequent settlement testing | D47: 1) Obtain the invoicewise breakup of debtors from the accounting software and agree the total balance to the Trial balance. 2) Calculate Ageing of debtors based on invoice date and group the debtors into outstanding for more than 1 year and less than 1 year 3) Check subsequent settlement of debtors and for those balances which are long outstanding and not susbequently settled, make enquiries with the management regarding their recoverability | G47: 60 | H47: 68 | I47: =+AVERAGE(G47,H47) -> 64
G48: 60 | H48: 68 | I48: =+AVERAGE(G48,H48) -> 64
B49: Receivables | C49: SPDRS2 - Obtain / prepare a schedule of provision for doubtful debts showing beginning balance, provision for doubtful accounts, write offs, recoveries and ending balance. Test the summarisation of the schedule and agree the ending balance to the general ledger. | D49: 1) Obtain management's policy of debtors provisioning and check if appropriate provision has been made for balances which are doubtful. 2) Prepare a schedule showing movement of debtors provision and agree the closing balance to the amunt booked in the ledger | G49: 16 | H49: 24 | I49: =+AVERAGE(G49,H49) -> 20
B50: Receivables | C50: SPDRS3 - Obtain supporting documents for bad debts written off to ensure that the write off has been approved by the appropriate authority. | D50: 1) Check whether appropriate approvals are present for the bad debts written off | G50: 4 | H50: 8 | I50: =+AVERAGE(G50,H50) -> 6
B51: Receivables | C51: SPDRS4 - Reconcile the total balance as per the ageing report to the general ledger and develop and expectation of the amount to be booked as provision for doubtful debts based on the management policy. Compare the same with the amount booked in the ledger and obtain explanations for the differences. | D51: 1) Prepare a schedule showing movement of debtors provision and agree the closing balance to the amunt booked in the ledger 2) For those debts which are long outstanding and no provision has been made, obtain reasons as to why provision has not been made | L51: Covered under SPDRS2
B52: Equity | C52: SPEQ1 - Obtain a schedule of changes in all equity accounts and all transactions affecting equity during the year. Agree the beginning balances of the schedule of changes in equity to prior-year working papers and agree the ending balances to the general ledger. Trace significant reconciling items, if any, to supporting documents. Agree changes in authorized shares to minutes and documents filed with the Registrar of Companies. Agree number of shares and proceeds from issuance of new shares to cash receipts and supporting records. | D52: 1) For corporate entitiies, review the minutes of BoD meetings and the MCA forms filed to see if there are any fresh issue of shares during the year. 2) For non coporate entities check whether withdrawals and additions to the capital and current accounts are accounted appropriately 3) Where dividends are declared in the case of corporate entities, check whether the required compliances have been met
B53: Equity | C53: SPEQ2 - Review minutes of meetings of those charged with governance noting dividends declared or distributed. For dividends paid in cash, trace selection to appropriate supporting documents, including meeting minutes. For dividends declared but unpaid, trace to recording to appropriate liability accounts. Ascertain the amount to be transferred to general reserve under Companies (Transfer of Profits to Reserves) Rules; compare with recorded amounts, investigate and correct all differences.
B54: Equity | C54: SPEQ3 - Ascertain the rate of dividend declared by the Board of Directors at their meeting to approve the annual audited financial statements; develop an expectation of the dividend payout and corporate dividend tax for the year; compare with recorded amounts, investigate and correct all differences
B55: Debt | C55: SPDBT1 - Obtain statements from the lenders and ensure that all the borrowings taken have been accounted in the general ledger. | D55: 1) Obtain statements from the lenders in respect of loans taken by the entity. Check whether loans taken and repayments made are correctly accounted
B56: Debt | C56: SPDBT2 - Obtain confirmation of account balances as on the balance sheet date from the lenders and agree the balances with the amount as per books. | D56: 1) Obtain balance confirmation statements directly from the lenders 2) If direct confirmations are not available, have the entity obtain confirmations and communicate the same to the auditors
B57: Debt | C57: SPDBT3 - Ensure that Tax has been deducted on all interest payments to the lenders | D57: 1) For loans taken from lenders other than banks, check whether tax deduction has been made at appropriate rates as specified in the income tax act
B58: Debt | C58: SPDBT4 - Check the amount of interest expense as per the statements and ensure that there are no material deviations from the amount booked in the ledger. | D58: 1) Compare the interest serviced as per the statement with the interest accounted in the ledger. Ensure that there are no differences
B59: Debt | C59: SPDBT5 - Recalculate the interest expense/compare the interest expense as per repayment schedule with the amounts booked | D59: 1) Recalculate the interest expense based on the outstanding balance and agreed interest rates to ensure that there has not been any overcharging of interest by the lenders. 2) If a repayment schedule is available, ensure that the interest charged by the lender is as per the repayment schedule
B60: Debt | C60: SPDBT6 - Wherever applicable, calculate and identify the portion of loan liability to be recogonised as current and as non-current | D60: 1) Classify the outstanding loan liability into current and non-current portions. 2) In case of finance leases, perform lease workings in order to identify the balance payable in each time frame as is required by the applicable financial reporting framework
B61: Accounts payable | C61: SPCL1 - Obtain the list of Creditors/ Creditors Trial Balance from the accounting package and agree the total with the balance as per general ledger. | D61: 1) Obtain the list of creditors from the accounting software and tally the total balance of the same with the creditors balance as per Trial balance | G61: 64 | H61: 72 | I61: =+AVERAGE(G61,H61) -> 68
B62: Accounts payable | C62: SPCL2 - Prepare or have the entity prepare balance confirmation requests for amounts outstanding to creditors as on the balance sheet date. Agree the balances as per confirmations received to the ledger balances and reconcile the differences if any. Incase of non replies, perform alternative procedures such as checking subsequent settlement of amounts outstanding and comparison with the original sales invoices. | D62: 1) Obtain confirmations from the creditors for balances outstanding to them 2) Where confirmation procedures are not performed, perform alternate procedures such as subsequent settlement procedures and comparison with original invoices to ensure that the balances are existent as on the balance sheet date | L62: Covered under SPCL1
B63: Accounts payable | C63: SPCL3 - Prepare a Collection-Remittance schedule for statutory dues and ensure that the statutory dues collected have been properly remitted within the due dates. Independantly recalculate the amount of statutory dues payable and compare the same with the amount booked in the ledger. | D63: 1) Independantly recalculate the statutory liabilities in respect of GST, TDS, Employee deductions, TCS etc as per the applicable provisions and ensure that there are no short deductions 2) Obtain payment challans from the entity for remittance of the statutory liabilities and check if there are any short payments
B64: Accounts payable | C64: SPCL4 - Obtain a breakup of the accrued expenses for the current period. Perform a retrospective review of significant accounting estimates related to accrued expenses and other liabilities of the prior year and consider the results of this retrospective review in evaluating the current-year estimates. If there exists a possible bias on the part of management in making accounting estimates, evaluate whether circumstances producing such a bias represent a risk of a material misstatement due to fraud. | D64: 1) Obtain a breakup of the accrued expenses (Expenses payable) as on the balance sheet date 2) Where accounting estimates are used by the entity in determining the expenses payable, check the underlying assumptions for the estimates and ensure if the same are appropriate in the circumstances. | O64: TDS | P64: GST
B65: Statutory Payables | C65: SPSP1- Independently recalculate the statutory liabilities by applying the relevant statutory provisions. | D65: 1) Obtain an understanding of the relevant statutory framework. 2) Obtain workings from the entity in respect of the statutory liabilities paid by them. 3) Independently recalculate the statutory laibilities at the applicable rates and compare the same with entity's working and amounts booked in the ledger | G65: 50 | H65: 70 | I65: =+O65 -> 60 | N65: SPSP1 | O65: 60
B66: Statutory Payables | C66: SPSP2- Ensure that any rate changes during the period are supported by appropriate notification/ammendments | D66: 1) Obtain notification/ammendments issued during the period under audit and ensure the correctness of applied rates. | L66: Covered under SPSP1 | N66: SPSP2 | O66: Covered under SPSP1
B67: Statutory Payables | C67: SPSP3- Verify the payments made in respect of statutory liablities with the respective challans for remittance. | D67: 1) Scrutinise the books, for payments made in respect of statutory dues made and obtain the challans as supportings. | G67: 10 | H67: 30 | I67: =+O67 -> 20 | N67: SPSP3 | O67: 20
B68: Statutory Payables | C68: SPSP4 - Ensure that the returns filed in respect of statutory liabilities contain all the details as is required by the statute | D68: 1) Compare the independent recalculations with the returns filed by the entity and check whether relevant details are included as required by the statute. | N68: SPSP4
B69: Loans & advances | C69: SPLA1 - Review the trial balance to identify expense accounts which are likely to include prepayments (viz., insurance, annual maintenance charges, etc.) | D69: 1) Review the trial balance to identify expense accounts which are likely to include prepayments (viz., insurance, annual maintenance charges, etc.) | F69: Grasion George | G69: 14 | H69: 18 | I69: =+AVERAGE(G69,H69) -> 16
B70: Loans & advances | C70: SPLA2 - Obtain the supporting documentation and independantly recalculate the amount to be booked as prepaid and the amount to be expensed off. | D70: 1) Obtain supportings for the amounts to be booked as prepaid expense and accordingly calculate the prepaid portion and expense portion | I70: =+AVERAGE(G70,H70) -> #DIV/0!
B71: Loans & advances | C71: SPLA3 - Obtain individual reconciliations of the selected prepaid account balances to the general ledger and trace the significant reconciling items if any to the supporting documentation. | D71: 1) Obtain breakups of other loans and advances balances and trace the balances to the supporting documentation if any | F71: Grasion George | G71: 10 | H71: 16 | I71: =+AVERAGE(G71,H71) -> 13
B72: Loans & advances | C72: SPLA4 - Check the subsequent settlement of the prepaid expenses (Loans & advances given). Incase of advances given to staff, obtain confirmations from the employees/management for the amount of loan/advance receivable. Write off amounts which are not recoverable | D72: 1) Perform subsequent settlement testing of staff advances as well as other advances. Write off advances which are deemed to be non recoverable 2) Obtain confirmations from employees in the case of staff advances. Also check whether the employee is still working with the entity | F72: Grasion George | G72: 35 | H72: 45 | I72: =+AVERAGE(G72,H72) -> 40
B73: Loans & advances | C73: SPLA5 - Obtain a breakup of the deposit accounts and test the validity of the account balance to the supporting documentations. If payments were not made in the current year, agree the opening balances to the previous year working papers. | D73: 1) Obtain supporting documents for deposits and verify the same with the amounts booked in the ledger | F73: Grasion George | G73: 15 | H73: 25 | I73: =+AVERAGE(G73,H73) -> 20
B74: Loans & advances | C74: SPLA6 - In respect of doubtful advances, develop and expectation of the amount to be booked as provision based on the management policy. Compare the same with the amount booked in the ledger and obtain explanations for the differences. In respect of writeoffs, obtain supporting documents foradvances written off to ensure that the write off has been approved by the appropriate authority | D74: 1) Obtain manamgement's policy for provisioning for doubtful advances, and develop an expectation of the amount to be booked as provision. Compare the same with the ledger and ensure there are no differences 2) In respect of advances written off, obtain appropriate approvals for the the writeoffs | L74: Covered under SPLA1 to SPLA5
B75: Loans & advances | C75: SPLA7 - Wherever applicable, calculate and identify the portion of advance or deposit to be recogonised as current and as non-current | D75: 1) Wherever applicable, calculate and identify the portion of advance or deposit to be recogonised as current and as non-current | L75: Covered under SPLA1 to SPLA5
B76: Revenue | C76: SPRE1 - Select samples of sales transactions recorded in the ledger and ensure the validity of the same by comparing with the relevant supporting documents available. | D76: 1) Select samples of sales transactions recorded in the ledger and ensure the validity of the same by comparing with the relevant supporting documents available.
B77: Revenue | C77: SPRE2 - Ensure that all Sales Invoices and Credit notes are sequentially numbered by the application system. | D77: 1) Try manually entering sales invoice number and credit note number in the system to ensure whether there are appropriate controls to ensure sequential numbering
B78: Revenue | C78: SPRE3 - Verify, on a sample basis that the sale prices and discounts given are as per the approved price list and the discount rates approved by the management. | D78: 1) Select sample invoices and ensure that the sale prices and discounts given therein are as per the management approved pricelist and discount chart
B79: Revenue | C79: SPRE4 - Compare, on a sample basis, the credit notes issued to customers in respect of sales returns with the corresponding sales invoices to ensure their validity. | D79: 1) Obtain samples of credit notes during the year 2) Compare the details mentioned in the credit notes with the original invoices and see whether the credit notes relate to valid sales made earlier
B80: Revenue
B81: Revenue | C81: SPRE6 - Obtain a list of last five shipping documents and return documents as on balance sheet date and first five shipping documents and return documents on the day suceeding the balance sheet date and ensure that the former has been accounted as sales while the latter has not. (Cutoff testing) | D81: 1) Obtain a list of last five shipping documents and return documents as on balance sheet date and first five shipping documents and return documents on the day suceeding the balance sheet date and ensure that the invoices related to the former have been accounted as sales while those related to the latter have not
B82: Operating expenses | C82: SPEXP1 - Select expense accounts for test of details/vouching on the basis of materiality set. Compare the selected expenses with appropriate supporting documents | D82: 1) Select expense ledgers for performing test of details based on the materiality levels set for the year. 2) From such selected expense ledgers, select the transactions for vouching based on the threshold materiality 3) Compare the selected transactions with relevant supporting documents | M82: Not vouched
B83: Operating expenses | C83: SPEXP2 - Perform expectation of administration, establishment expenses on the basis of external supporting documents available such as rent agreements, contracts for professional services etc and compare with amounts booked in ledger | D83: 1) In respect of recurring expenses such as rent, professional services etc, obtain the contract with the respective parties and ensure that the accounting of expenses is correct

Sheet Fixed Assets
B2: Dhathri Ayurkendra Private Limited
B3: Statutory Audit for the year ended 31.03.2018
B5: Account Balance | D5: Fixed Assets
B7: Audit objectives, Risk assessment and Responses to assessed risks
B8: Sl No | C8: Risks Identified | D8: Due to Fraud? | E8: Assertion | F8: Control Activity | G8: Planning to rely on Controls? | H8: Planned Substantive procedures | I8: Description of Substantive procedures
B9: 1 | C9: Risk of understatement of fixed assets because assets acquired by the entity are not recorded. | D9: No | E9: Completeness | F9: 1) Periodic counts of fixed assets are performed and reconciled to the fixed asset register / general ledger. | G9: Yes | H9: FA 2 FA 3 | I9: - Additions Testing - Physical Verification
B10: 2 | C10: Risk of understatement of fixed assets because assets in use and still owned by the entity have been wrongly recorded as disposed. | D10: No | E10: Completeness | G10: Yes | H10: FA 2 FA 3 FA 4 | I10: - Additions Testing - Physical Verification - Asset Deletions
B11: 3 | C11: Risk of understatement of fixed assets because fixed assets purchased have been expensed and not capitalised. | D11: No | E11: Completeness | F11: 1) Periodic counts of fixed assets are performed and reconciled to the fixed asset register. 2) Management reviews and approves the journal voucher along with appropriate supporting documentation before recording asset related transactions in the fixed asset register / general ledger. | G11: Yes | H11: FA 2 FA 6 | I11: - Additions Testing - Repairs & Maint - vouching
B12: 4 | C12: Risk of understatement of fixed assets because assets purchased prior to period end have not been recorded at or before the period end. | D12: No | E12: Completeness | G12: Yes | H12: FA 2 FA 6 | I12: - Additions Testing - Repairs & Maint - vouching
B13: 5 | C13: Risk of understatement of fixed assets because depreciation has been recorded for fictitious assets and / or assets that have been disposed of. | D13: No | E13: Completeness, Existence, Rights and obligations | F13: NO SPECIFIC CONTROL ACTIVITY DEFINED AS DEPRECIATION IS CALCULATED BY THE AUDITORS AT THE TIME OF THE AUDIT | G13: No | H13: FA 3 FA 4 FA 5 | I13: - Physical Verification - Asset Deletions - Depreciation computation
B14: 6 | C14: Risk of overstatement of fixed assets because repairs and maintenance expenses have been incorrectly capitalised as fixed assets. | D14: No | E14: Existence, Rights and obligations | F14: 1) Periodic counts of fixed assets are performed and reconciled to the fixed asset register. 2) Management reviews and approves the journal voucher along with appropriate supporting documentation before recording asset related transactions in the fixed asset register / general ledger. | G14: Yes | H14: FA 2 FA 3 FA 6 | I14: - Additions Testing - Physical Verification - Repairs & Maint - vouching
B15: 7 | C15: Risk of overstatement of fixed assets because assets disposed of have not been recorded in the fixed asset register / general ledger. | D15: No | E15: Existence, Rights and obligations | F15: 1) Periodic counts of fixed assets are performed and reconciled to the fixed asset register / general ledger. | G15: Yes | H15: FA 4 | I15: - Asset Deletions
B16: 8 | C16: Risk of overstatement of fixed assets because assets purchased subsequent to period end have been incorrectly recorded before the period end. | D16: No | E16: Existence, Rights and obligations | F16: 1) Management reviews and approves the journal voucher along with appropriate supporting documentation before recording asset related transactions in the fixed asset register / general ledger. | G16: Yes | H16: FA 2 | I16: - Additions Testing
B17: 9 | C17: Risk of overstatement of fixed assets because obsolete / damaged / unusable assets have not been written down to their recoverable value. | D17: No | E17: Valuation and allocation | F17: 1) Periodic counts of fixed assets are performed and reconciled to the fixed asset register / general ledger. | G17: Yes | H17: FA 4 | I17: - Asset Deletions
B18: 10 | C18: Risk of misstatement of fixed assets because cost, depreciation expense and accumulated depreciation as per general ledger do not agree with the fixed asset register. | D18: No | E18: Valuation and allocation, Existence, Completeness | F18: NO SPECIFIC CONTROL ACTIVITY DEFINED AS DEPRECIATION IS CALCULATED BY THE AUDITORS AT THE TIME OF THE AUDIT | G18: No | H18: FA 1 FA 2 FA 4 FA 5 | I18: - OB Testing - Additions Testing - Asset Deletions - Depreciation computation
B19: 11 | C19: Risk of overstatement of fixed assets because impairment to assets have not been recorded. | D19: No | E19: Valuation and allocation | F19: NO SPECIFIC CONTROL ACTIVITY DEFINED AS IMPAIREMENT TO ASSETS IS CALCULATED BY THE AUDITORS AT THE TIME OF THE AUDIT | G19: No | H19: FA 7 | I19: - Impairment Testing
B20: 12 | C20: Risk of misstatement of fixed assets because the depreciation method and / or depreciation rate adopted are not in compliance with the Companies Act / Indian GAAP / Accounting Policy approved by the Management. | D20: No | E20: Valuation and allocation | F20: NO SPECIFIC CONTROL ACTIVITY DEFINED AS DEPRECIATION IS CALCULATED BY THE AUDITORS AT THE TIME OF THE AUDIT | G20: No | H20: FA 1 FA 2 FA 4 FA 5 | I20: - OB Testing - Additions Testing - Asset Deletions - Depreciation computation
B21: 13 | C21: Risk of misstatement of fixed assets because fixed asset register includes fictitious assets or assets which do not exist. | D21: No | E21: Existence, Rights and obligations | F21: 1) Periodic counts of fixed assets are performed and reconciled to the fixed asset register. 2) Management reviews and approves the journal voucher along with appropriate supporting documentation before recording asset related transactions in the fixed asset register / general ledger. | G21: Yes | H21: FA 1 FA 2 FA 3 FA 4 | I21: - OB Testing - Additions Testing - Physical Verification - Asset Deletions
B22: 14 | C22: Risk of misstatement of fixed assets because asset acquisitions and disposals have not been approved by the Management. | D22: No | E22: Existence, Rights and obligations | F22: 1) Management reviews and approves the journal voucher along with appropriate supporting documentation before recording asset related transactions in the fixed asset register / general ledger. | G22: Yes | H22: FA 2 FA 3 FA 4 | I22: - Additions Testing - Physical Verification - Asset Deletions
B23: 15 | C23: Risk of misstatement of fixed assets because depreciation calculated by the application system is incorrect / invalid. | D23: No | E23: Valuation and allocation | F23: NO SPECIFIC CONTROL ACTIVITY DEFINED AS DEPRECIATION IS CALCULATED BY THE AUDITORS AT THE TIME OF THE AUDIT | G23: No | H23: FA 1 FA 2 FA 4 FA 5 | I23: - OB Testing - Additions Testing - Asset Deletions - Depreciation computation
B25: List of Substantive procedures
B26: Sl No | C26: Descriprion of Substantive Procedure | E26: Assertion Addressed | F26: WP Reference
B27: FA 1 | C27: Ensure that the opening balance of Fixed assets have been correctly carried forward from the previous reporting period | E27: Valuation, Completeness | F27: Refer [Opening Balance Verification workings]
B28: FA 2 | C28: Obtain a list of Fixed Asset additions during the period and compare the amounts booked in the ledger with the relevant supporting documents. Ensure that all additions during the year have been correctly booked in the respective ledger accounts. | E28: Valuation, Completeness, Rights and Obligations | F28: Refer [FA Additions vouching]
B29: FA 3 | C29: Obtain the records of the physical verification procedures carried out by the entity during the year. Alternatively, we may choose to visit a few locations on our own and physically verfiy the assets. | E29: Existence, Rights and Obligations | F29: Physical Verification of Fixed assets done by management
B30: FA 4 | C30: Obtain a list of Asset Disposals during the year and ensure that the related amounts have been correctly removed from the Gross Block as well as Accumulated Depreciation | E30: Valuation, Completeness | F30: There are no Asset disposals during the period under audit
B31: FA 5 | C31: Obtain the rates of Deprecation for each category of assets as per the Companies Act as well as the Income Tax act and compute the Depreciation Expense for the year as per Companies Act and income Tax Act. | E31: Valuation, Completeness | F31: Refer [Depreciation workings as per Companies Act]
F32: Refer [Depreciation workings as per Income Tax Act]
B33: FA 6 | C33: Review the Repairs and maintanence ledger to ensure that no asset which has to be capitalised has been wrongly expensed off | E33: Completeness | F33: Refer [Expense Vouching workings]
B34: FA 7 | C34: During the current period, determine whether any of the following factors are present or whether there are other events or changes in circumstances that indicate the carrying amount of a long-lived asset that the entity expects to hold and use may not be recoverable: (1) A significant decrease in the market price of a long-lived asset. (2) A significant adverse change in the extent or manner in which a long-lived asset is being used or in its physical condition. (3) A significant adverse change in legal factors or in the business climate that could affect the value of a long-lived asset, including an adverse action or assessment by a regulator. (4) An accumulation of costs significantly in excess of the amount originally expected for the acquisition or construction of a long-lived asset. (5) A current-period operating or cash flow loss combined with a history of operating or cash flow losses or a projection or forecast that demonstrates continuing losses associated with the use of a long-lived asset. (6) A current expectation that, more likely than not, a long-lived asset will be sold or otherwise disposed of significantly before the end of its previously estimated useful life. | E34: Valuation and Allocation | F34: There are no factors indicating non recoverability of the carrying amount/impairment of an asset

Sheet NET Summary
D2: Expected Man hours
B3: Material class of transaction | C3: Task | D3: Min | E3: Max | F3: Avg | G3: Rate | H3: Average Cost | J3: Hrs | K3: Man days | L3: Required resource | M3: Man days
B4: Fixed Assets | D4: =SUMIF(#REF!,'NET Summary'!$B4,#REF!) -> #REF! | E4: =SUMIF(#REF!,'NET Summary'!$B4,#REF!) -> #REF! | F4: =SUMIF(#REF!,'NET Summary'!$B4,#REF!) -> #REF! | G4: =SUMIF(#REF!,'NET Summary'!$B4,#REF!) -> #REF! | H4: =SUMIF(#REF!,'NET Summary'!$B4,#REF!) -> #REF! | M4: =F4/8 -> #REF!
C5: FA Workings (including CWIP) | J5: 96 | K5: =SUM(J5/8) -> 12 | L5: Linson Francis
C6: FA Vouching (including CWIP) | J6: 12 | K6: =SUM(J6/8) -> 1.5 | L6: First year article
C7: FA Control testing | J7: 4 | K7: =SUM(J7/8) -> 0.5 | L7: First year article
C8: FA Review | J8: 16 | K8: =SUM(J8/8) -> 2 | L8: Govind P
B9: Debt | D9: =SUMIF(#REF!,'NET Summary'!$B9,#REF!) -> #REF! | E9: =SUMIF(#REF!,'NET Summary'!$B9,#REF!) -> #REF! | F9: =SUMIF(#REF!,'NET Summary'!$B9,#REF!) -> #REF! | G9: =SUMIF(#REF!,'NET Summary'!$B9,#REF!) -> #REF! | H9: =SUMIF(#REF!,'NET Summary'!$B9,#REF!) -> #REF! | M9: =F9/8 -> #REF!
C10: Kuri Loans | J10: 16 | K10: =SUM(J10/8) -> 2 | L10: Shahin Shah
C11: Vehicle Loans | J11: 4 | K11: =SUM(J11/8) -> 0.5 | L11: Dheeraj R
C12: Working Capital Loans | J12: 4 | K12: =SUM(J12/8) -> 0.5 | L12: Dheeraj R
C13: Debt Review | J13: 8 | K13: =SUM(J13/8) -> 1 | L13: Govind P
B14: Statutory Payables | D14: =SUMIF(#REF!,'NET Summary'!$B14,#REF!) -> #REF! | E14: =SUMIF(#REF!,'NET Summary'!$B14,#REF!) -> #REF! | F14: =SUMIF(#REF!,'NET Summary'!$B14,#REF!) -> #REF! | G14: =SUMIF(#REF!,'NET Summary'!$B14,#REF!) -> #REF! | H14: =SUMIF(#REF!,'NET Summary'!$B14,#REF!) -> #REF! | M14: =F14/8 -> #REF!
C15: GST Exporting and formating | J15: =K15*8 -> 72 | K15: 9 | L15: First year article
C16: Input workings | J16: =K16*8 -> 24 | K16: 3 | L16: Dheeraj R
C17: GST Output workings | J17: =K17*8 -> 16 | K17: 2 | L17: Linson Francis
C18: GST Output workings | J18: =K18*8 -> 16 | K18: 2 | L18: First year article
C19: GST Consolidation | J19: =K19*8 -> 40 | K19: 5 | L19: Linson Francis
C20: GST Financial summary | J20: =K20*8 -> 12 | K20: 1.5 | L20: Linson Francis
C21: TDS/TCS | J21: =K21*8 -> 80 | K21: 10 | L21: Grasion George
C22: TDS/TCS Exporting | J22: =K22*8 -> 16 | K22: 2 | L22: Grasion George
C23: Statutory payable review | J23: 24 | K23: 3 | L23: Govind P
C24: Statutory payable review | J24: 24 | K24: 3 | L24: Grasion/ Linson
B25: Cash & Bank | D25: =SUMIF(#REF!,'NET Summary'!$B25,#REF!) -> #REF! | E25: =SUMIF(#REF!,'NET Summary'!$B25,#REF!) -> #REF! | F25: =SUMIF(#REF!,'NET Summary'!$B25,#REF!) -> #REF! | G25: =SUMIF(#REF!,'NET Summary'!$B25,#REF!) -> #REF! | H25: =SUMIF(#REF!,'NET Summary'!$B25,#REF!) -> #REF! | M25: =F25/8 -> #REF!
C26: Bank Reconciliation | J26: 16 | K26: =SUM(J26/8) -> 2 | L26: First year article
C27: Cash & Bank Review | J27: 4 | K27: =SUM(J27/8) -> 0.5 | L27: Govind P
B28: Payroll | D28: =SUMIF(#REF!,'NET Summary'!$B28,#REF!) -> #REF! | E28: =SUMIF(#REF!,'NET Summary'!$B28,#REF!) -> #REF! | F28: =SUMIF(#REF!,'NET Summary'!$B28,#REF!) -> #REF! | G28: =SUMIF(#REF!,'NET Summary'!$B28,#REF!) -> #REF! | H28: =SUMIF(#REF!,'NET Summary'!$B28,#REF!) -> #REF! | M28: =F28/8 -> #REF!
C29: Payroll workings | J29: 40 | K29: =SUM(J29/8) -> 5 | L29: Arun K Baiju
C30: Payroll Review | J30: 8 | K30: =SUM(J30/8) -> 1 | L30: Govind P
B31: Inventory | D31: =SUMIF(#REF!,'NET Summary'!$B31,#REF!) -> #REF! | E31: =SUMIF(#REF!,'NET Summary'!$B31,#REF!) -> #REF! | F31: =SUMIF(#REF!,'NET Summary'!$B31,#REF!) -> #REF! | G31: =SUMIF(#REF!,'NET Summary'!$B31,#REF!) -> #REF! | H31: =SUMIF(#REF!,'NET Summary'!$B31,#REF!) -> #REF! | M31: =F31/8 -> #REF!
C32: Inventory Exporting | J32: =14*8 -> 112 | K32: =SUM(J32/8) -> 14 | L32: Nevil + 1 First year article | O32: =J32/2 -> 56
C33: Inventory - Data bank | J33: =12*8 -> 96 | K33: =SUM(J33/8) -> 12 | L33: Nevil + Linson Francis + Grasion George
C34: Inventory - FIFO | J34: 24 | K34: =SUM(J34/8) -> 3 | L34: Nevil + 1 First year article
C35: Inventory - Opening balance correction | J35: 16 | K35: =SUM(J35/8) -> 2 | L35: Nevil + 1 First year article
C36: Inventory - Review | J36: 16 | K36: =SUM(J36/8) -> 2 | L36: Govind P
C37: Inventory - Review | J37: 32 | K37: =SUM(J37/8) -> 4 | L37: Grasion George + Nevil
C38: Inventory - Others | J38: 24 | K38: =SUM(J38/8) -> 3 | L38: Grasion George + Nevil
B39: Receivables | D39: =SUMIF(#REF!,'NET Summary'!$B39,#REF!) -> #REF! | E39: =SUMIF(#REF!,'NET Summary'!$B39,#REF!) -> #REF! | F39: =SUMIF(#REF!,'NET Summary'!$B39,#REF!) -> #REF! | G39: =SUMIF(#REF!,'NET Summary'!$B39,#REF!) -> #REF! | H39: =SUMIF(#REF!,'NET Summary'!$B39,#REF!) -> #REF! | M39: =F39/8 -> #REF!
C40: Receivables - Accuracy of client workings | J40: =K40*8 -> 8 | K40: 1 | L40: First year article
C41: Receivables - Confirmations | J41: =K41*8 -> 16 | K41: 2 | L41: First year article
C42: Receivables - Provision | J42: =K42*8 -> 8 | K42: 1 | L42: Grasion George
C43: Receivables - Review | J43: =K43*8 -> 8 | K43: 1 | L43: Grasion George
C44: Receivables - Review | J44: =K44*8 -> 8 | K44: 1 | L44: Govind P
B45: Accounts payable | D45: =SUMIF(#REF!,'NET Summary'!$B45,#REF!) -> #REF! | E45: =SUMIF(#REF!,'NET Summary'!$B45,#REF!) -> #REF! | F45: =SUMIF(#REF!,'NET Summary'!$B45,#REF!) -> #REF! | G45: =SUMIF(#REF!,'NET Summary'!$B45,#REF!) -> #REF! | H45: =SUMIF(#REF!,'NET Summary'!$B45,#REF!) -> #REF! | M45: =F45/8 -> #REF!
C46: Accounts Payable - Accuracy of client workings | J46: =K46*8 -> 8 | K46: 1 | L46: First year article
C47: Accounts Payable - Confirmations | J47: =K47*8 -> 16 | K47: 2 | L47: First year article
C48: Accounts Payable - Provision | J48: =K48*8 -> 8 | K48: 1 | L48: Grasion George
C49: Accounts Payable - Review | J49: =K49*8 -> 8 | K49: 1 | L49: Grasion George
C50: Accounts Payable - Review | J50: =K50*8 -> 8 | K50: 1 | L50: Govind P
B51: Loans & advances | D51: =SUMIF(#REF!,'NET Summary'!$B51,#REF!) -> #REF! | E51: =SUMIF(#REF!,'NET Summary'!$B51,#REF!) -> #REF! | F51: =SUMIF(#REF!,'NET Summary'!$B51,#REF!) -> #REF! | G51: =SUMIF(#REF!,'NET Summary'!$B51,#REF!) -> #REF! | H51: =SUMIF(#REF!,'NET Summary'!$B51,#REF!) -> #REF! | M51: =F51/8 -> #REF!
C52: Rent Deposits | J52: =K52*8 -> 8 | K52: 1 | L52: First year article
C53: Other Deposits | J53: =K53*8 -> 16 | K53: 2 | L53: First year article
C54: Staff Advance | J54: =K54*8 -> 16 | K54: 2 | L54: First year article
C55: Prepaid expense | J55: =K55*8 -> 8 | K55: 1 | L55: First year article
C56: Deposits with Govt. Authorities | J56: =K56*8 -> 8 | K56: 1 | L56: Grasion George
C57: Loans and advances Review | J57: =K57*8 -> 16 | K57: 2 | L57: Govind P
C58: Loans and advances Review | J58: =K58*8 -> 16 | K58: 2 | L58: Grasion George
B59: Revenue | D59: =SUMIF(#REF!,'NET Summary'!$B59,#REF!) -> #REF! | E59: =SUMIF(#REF!,'NET Summary'!$B59,#REF!) -> #REF! | F59: =SUMIF(#REF!,'NET Summary'!$B59,#REF!) -> #REF! | G59: =SUMIF(#REF!,'NET Summary'!$B59,#REF!) -> #REF! | H59: =SUMIF(#REF!,'NET Summary'!$B59,#REF!) -> #REF! | M59: =F59/8 -> #REF!
C60: Revenue related vouching | J60: =K60*8 -> 40 | K60: 5 | L60: First year article
C61: Revenue Review | J61: 4 | K61: 0.5 | L61: Govind P
B62: Operating expenses | D62: =SUMIF(#REF!,'NET Summary'!$B62,#REF!) -> #REF! | E62: =SUMIF(#REF!,'NET Summary'!$B62,#REF!) -> #REF! | F62: =SUMIF(#REF!,'NET Summary'!$B62,#REF!) -> #REF! | G62: =SUMIF(#REF!,'NET Summary'!$B62,#REF!) -> #REF! | H62: =SUMIF(#REF!,'NET Summary'!$B62,#REF!) -> #REF! | M62: =F62/8 -> #REF!
C63: Sample Selection | J63: 8 | K63: 1 | L63: Linson Francis
C64: Vouching | J64: 40 | K64: =J64/8 -> 5 | L64: 2 First Year article
B65: Financials | D65: =SUMIF(#REF!,'NET Summary'!$B65,#REF!) -> #REF! | E65: =SUMIF(#REF!,'NET Summary'!$B65,#REF!) -> #REF! | F65: =SUMIF(#REF!,'NET Summary'!$B65,#REF!) -> #REF! | G65: =SUMIF(#REF!,'NET Summary'!$B65,#REF!) -> #REF! | H65: =SUMIF(#REF!,'NET Summary'!$B65,#REF!) -> #REF! | J65: 40 | K65: =J65/8 -> 5 | L65: Linson Francis | M65: =F65/8 -> #REF!
B66: Opening balance verification | D66: =SUMIF(#REF!,'NET Summary'!$B66,#REF!) -> #REF! | E66: =SUMIF(#REF!,'NET Summary'!$B66,#REF!) -> #REF! | F66: =SUMIF(#REF!,'NET Summary'!$B66,#REF!) -> #REF! | G66: =SUMIF(#REF!,'NET Summary'!$B66,#REF!) -> #REF! | H66: =SUMIF(#REF!,'NET Summary'!$B66,#REF!) -> #REF! | J66: 12 | K66: =J66/8 -> 1.5 | L66: Linson Francis | M66: =F66/8 -> #REF!
B67: Audit documentation | D67: =SUMIF(#REF!,'NET Summary'!$B67,#REF!) -> #REF! | E67: =SUMIF(#REF!,'NET Summary'!$B67,#REF!) -> #REF! | F67: =SUMIF(#REF!,'NET Summary'!$B67,#REF!) -> #REF! | G67: =SUMIF(#REF!,'NET Summary'!$B67,#REF!) -> #REF! | H67: =SUMIF(#REF!,'NET Summary'!$B67,#REF!) -> #REF! | M67: =F67/8 -> #REF!
B68: Statutory Audit Review | D68: =SUMIF(#REF!,'NET Summary'!$B68,#REF!) -> #REF! | E68: =SUMIF(#REF!,'NET Summary'!$B68,#REF!) -> #REF! | F68: =SUMIF(#REF!,'NET Summary'!$B68,#REF!) -> #REF! | G68: =SUMIF(#REF!,'NET Summary'!$B68,#REF!) -> #REF! | H68: =SUMIF(#REF!,'NET Summary'!$B68,#REF!) -> #REF! | M68: =F68/8 -> #REF!
B69: Total | H69: =SUM(H4:H68) -> #REF!

Sheet ROMM & FAP summary - FS level
B2: ROMM and FAP at Financial statement Level (For details of FS level FAP, refer below; For MCOTABD level FAP, refer ensuing sheets)
B4: WP Reference | C4: Risks Identified | D4: Resulting in FS level risk | E4: Whether Pervasive? | F4: Management Plans to address Risk | G4: Further Audit Procedures Planned / Remarks of Auditor
B5: [2020.01 Understanding the entity] | C5: The relationships with suppliers and customers are generally cordial. Rawmaterial imported is supplied against advances paid to suppliers which is not against any contract and therefore there is risk that the party may not honour the purchase transaction | D5: Yes | E5: Yes | F5: The management relies on the long term association they have had with the supplier and is of the opinion that this risk is not material. Further, advance paid at the time of placing an import order is only 15% of the import value after which the supplier starts manufacturing the required batch. Further the entity's agent who facilitates the import transactions acts as an extended arm of the entity and effectively coordinates the transaction. | G5: SPCL6 - Subsequent transactions testing | H5: GRN, Qlty testing etc
B6: [2020.01 Understanding the entity] | C6: Rule 3 of Companies Accounts Rules becomes applicable from 01-04-2023.However rule 11(g) of Companies (Audit and Auditors)Rules becomes applicable from 01-04-2022. | D6: Yes | E6: Yes | F6: Accounting softwares used by entity namely Tallyprime and SAP having audit trial feature. | G6: Testing General IT controls and Application level controls
B7: [2020.01 Understanding the entity] | C7: Risks arising due to overall market conditions including but not limited to price changes of commodities, governmental policies, pandemics etc | D7: Yes | E7: Yes | F7: While preplanning and following a conservative approach to business may alleviate some of these risks, in respect of certain risks, the management will be able to respond only when such risk arises | G7: FAPFS1 to FAPFS 10 given below
B8: [2020.02 Understanding the internal control] | C8: TCWG may inadvertently encroach on the roles and responsibilities of operational management, also play the role of operational management leading to confusion, overlapping duties, or undermining the authority of senior personnel. This can cause friction within the management team, reducing efficiency and effectiveness in decision-making processes. | D8: Yes | E8: Yes | F8: TCWG has delegated certain operational responsibilities to senior management, empowering them to make decisions within their areas of expertise. This Fosters a culture of trust and accountability, allowing senior personnel to lead effectively while TCWG focuses on strategic governance. | G8: It was explained that the entity is in the process of improvising its operations and accordingly there are structural changes happening. The present involvement of TCWG in operations was warranted since the entity reported losses in the year 2022-23 and the directors took a call to take part more in the operational activities in order to tide over the situation and steady the ship. It was informed that their involvement in the operations will be brought down going forward.
B9: [2020.02 Understanding the internal control] | C9: Absence of a formal documented risk assessment process would mean that risks may not be identified or managed effectively, leading to unforeseen issues that could impact the organization’s performance and stability. | D9: Yes | E9: Yes | F9: Active involvement of TCWG in the management has so far ensured that the entity was not caught in any surprise situations due to business risks that impacted the organisation's performance and stability. Further, as per the provisions of Companies act, a third party internal auditor has been appointed by the entity and the entity is planning to move to a risk based internal audit approach this year the scope of which is being finalised. Iit is expected that a formal documented risk assessment process with risk rankings and matrices will be introduced as part of the same | G9: The entity has the capability and resources to appropriately identify, assess and responds to risks as and when they occur even though such process is not documented or formal. Based on our risk assessment process, we observed that the entity has in place adequate controls to respond to risks at business level, FS level and MCOTABD level. The results of the same are given in the respective working papers FAPFS3 - Monitoring of work FAPFS4 - Unpredictable elements FAPFS5 - Audit procedures to obtain persuasive audit evidence
B10: [2020.02 Understanding the internal control] | C10: Non standard journal entries may be used to misrepresent books of account by artificially overstanding or understanding account balances | D10: Yes | E10: No | F10: There is proper control over passing of non standard journal entries in that such rights are limited to select individuals within the organisation | G10: Non standard journal entries are checked during ledger scrutiny FAPFS7 - Journal entry testing
B11: [2020.02 Understanding the internal control] | C11: Control activities at the entity including Authorisation matrices, segregation etc are not documented. | D11: Yes | E11: Yes | F11: It is ensured that eventhough the activities are not documented, there is an in principle system at the entity to ensure that the same are appropriately being followed. Further, as per the provisions of Companies act, an "external" internal auditor has been appointed by the entity and the entity is planning to move to a risk based internal audit approach this year the scope of which is being finalised. Iit is expected that a formal documented risk assessment process with risk rankings and related control activities will be introduced as part of the same | G11: Based on our risk assessment process, we observed that the entity has in place adequate controls to respond to risks at business level, FS level and MCOTABD level. The results of the same are given in the respective working papers FAPFS1 - Engagement team selection FAPFS2 - Firm's QC policy FAPFS3 - Monitoring of work FAPFS4 - Unpredictable elements FAPFS5 - Audit procedures to obtain persuasive audit evidence FAPFS6 - Results of audit procedures from prior years
B12: [2020.01 Understanding the entity] | C12: Risk that all events occurring between the date of the financial statements and the date of the auditor’s report that require adjustment of, or disclosure in, the financial statements are not identified | D12: Yes | E12: Yes | F12: The management prepares monthly financial results for discussing with TCWG. Significant transactions occuring after the balance sheet date are therefore appropriately captured | G12: FAPFS8 - Reviewing subsequent period MIS reports and financial statements FAPFS9 - Reviewing minutes of meeting of BoD Perform inquiries with the management and TCWG on occurrence of significant subsequent events.
B13: [2020.01 Understanding the entity] | C13: Risk that significant related party relationships and transactions are not identified, accounted and appropriately disclosed in the financial statements | D13: Yes | E13: Yes | F13: Related party registers and register of contracts are maintained and related party transactions are entered only after details of the related party are entered in such registers | G13: FAPFS10 - Management representations, statutory registers
B18: Overall responses to assessed risks of misstatement at financial statement level
B19: FAP Code | C19: Description of procedure | G19: Reference
B20: FAPFS1 | C20: The audit engagement team was finalised considering the experience and skill sets of the team members. Staff with prior experience in handling audits of the same entity are selected. The significant audit areas are assigned to team members considering their relative experience and special skills | G20: Engagement Team
B21: FAPFS2 | C21: Meetings are conducted during various stages of the audit process. At the time of commencement of audit, the engagement partner/qualified member explains to the entire team the need to maintain professional skepticism and adherance to ethical requirements throughout the audit. The firm's quality control manual is explained to the team members so that they have an overall idea about the responsibilities towards quality control in an engagement. The significant audit areas are also communicated to the members where more focus and attention of the team is required. | G21: Meeting Minutes
B22: FAPFS3 | C22: The progress of the audit work is closely and periodically monitored by the engagement partner/qualified member so that queries and roadblocks that the engagement team may face while performing the audit engagement are addressed on an immediate basis | G22: Refer Monitoring MoM
B23: FAPFS4 | C23: Unpredictable elements are included as part of the audit procedures such as surprise verification of cash, inventory etc. Additional audit procedures are performed in respect of risks identified as significant risks. | G23: Refer respective Manual WPs
B24: FAPFS5 | C24: The audit procedures are performed at the period end rather than at an interim date. Audit procedures to obtain more extensive and persuasive audit evidence are performed by the auditor in respect of those areas which in the auditor's professional judgement are considered as significant audit areas | G24: 4000-Audit Execution
B25: FAPFS6 | C25: The entity has an effective control environment as per the auditor's evaluation. From prior experiences with the entity, it has been noted that there are sound systems and controls in place at the entity and the management as well as TCWG attach a lot of importance to maintain an effective control environment. Further, the auditor obtained details of control activities in place at the entity. These were reviewed by the auditor and reliance was placed on some of these control activities. The control activities relied upon by the auditor were tested during the audits for the FYs 2022-23 and 2023-24. Where the controls continue to be relevant and no major changes have occured, such a control need to be tested only once in every 3 audits. However, during the year 2024-25 it was ensured that all control activities on which the auditor chooses to rely upon were tested | G25: FAP - Test of controls
G26: FAP - MCOTABD
B27: FAPFS7 | C27: Siginificant and unusual entries (specifically journal entries) made in the books of account are checked as part of ledger scrutiny to seen if they are genuine entries
B28: FAPFS8 | C28: Obtain MIS reports and financial statements prepared for the subsequent period by the management. Check if there are any significant transactions reported therein after the balancesheet date but before the date of auditor's report which require adjustment or disclosure in the financial statements | G28: SA 560 - Subsequent events
B29: FAPFS9 | C29: Obtain minutes of meeting by the board of directors and check if there are any significant events, decisions or transactions reported therein after the balancesheet date but before the date of auditor's report which require adjustment or disclosure in the financial statements
B30: FAPFS10 | C30: Obtain management representations regarding the list of related parties of the company. Identify related party transactions from the books of account and ensure that the same are appropriately disclosed in the financial statements. Obtain register of contracts maintained by the company and check the correctness of related party relationships and transactions recorded therein | G30: 3000 - Communications

Sheet Sheet1
B2: Account Balance | C2: Risks Identified | D2: Assertions addressed | I2: No of assertions addressed | J2: Assertions addressed
B3: Fixed Assets | C3: RSKFA1 - Risk of understatement of fixed assets because assets acquired by the entity are not recorded. | D3: P&D | E3: C | F3: V | I3: 5 | J3: E | K3: R | L3: C | M3: V | N3: A | Q3: =D3&$C3 -> P&DRSKFA1 - Risk of understatement of fixed assets because assets acquired by the entity are not recorded. | R3: =E3&$C$3 -> CRSKFA1 - Risk of understatement of fixed assets because assets acquired by the entity are not recorded. | S3: =F3&$C$3 -> VRSKFA1 - Risk of understatement of fixed assets because assets acquired by the entity are not recorded.
B4: Fixed Assets | C4: RSKFA2 - Risk of understatement of fixed assets because assets in use and still owned by the entity have been wrongly recorded as disposed. | D4: E | E4: R | F4: C | G4: V | Q4: =D4&$C4 -> ERSKFA2 - Risk of understatement of fixed assets because assets in use and still owned by the entity have been wrongly recorded as disposed. | R4: =E4&$C4 -> RRSKFA2 - Risk of understatement of fixed assets because assets in use and still owned by the entity have been wrongly recorded as disposed. | S4: =F4&$C4 -> CRSKFA2 - Risk of understatement of fixed assets because assets in use and still owned by the entity have been wrongly recorded as disposed. | T4: =G4&$C4 -> VRSKFA2 - Risk of understatement of fixed assets because assets in use and still owned by the entity have been wrongly recorded as disposed.
B5: Fixed Assets | C5: RSKFA3 - Risk of understatement of fixed assets because fixed assets purchased have been expensed and not capitalised. | D5: E | E5: R | F5: V | G5: A | Q5: =D5&$C5 -> ERSKFA3 - Risk of understatement of fixed assets because fixed assets purchased have been expensed and not capitalised. | R5: =E5&$C5 -> RRSKFA3 - Risk of understatement of fixed assets because fixed assets purchased have been expensed and not capitalised. | S5: =F5&$C5 -> VRSKFA3 - Risk of understatement of fixed assets because fixed assets purchased have been expensed and not capitalised. | T5: =G5&$C5 -> ARSKFA3 - Risk of understatement of fixed assets because fixed assets purchased have been expensed and not capitalised.
B6: Fixed Assets | C6: RSKFA4 - Risk of overstatement of fixed assets because repairs and maintenance expenses have been incorrectly capitalised as fixed assets. | D6: E | E6: R | F6: V | G6: A | Q6: =D6&$C6 -> ERSKFA4 - Risk of overstatement of fixed assets because repairs and maintenance expenses have been incorrectly capitalised as fixed assets. | R6: =E6&$C6 -> RRSKFA4 - Risk of overstatement of fixed assets because repairs and maintenance expenses have been incorrectly capitalised as fixed assets. | S6: =F6&$C6 -> VRSKFA4 - Risk of overstatement of fixed assets because repairs and maintenance expenses have been incorrectly capitalised as fixed assets. | T6: =G6&$C6 -> ARSKFA4 - Risk of overstatement of fixed assets because repairs and maintenance expenses have been incorrectly capitalised as fixed assets.
B7: Fixed Assets | C7: RSKFA5 - Risk of overstatement of fixed assets because assets disposed of have not been recorded in the fixed asset register / general ledger. | D7: E | E7: R | Q7: =D7&$C7 -> ERSKFA5 - Risk of overstatement of fixed assets because assets disposed of have not been recorded in the fixed asset register / general ledger. | R7: =E7&$C7 -> RRSKFA5 - Risk of overstatement of fixed assets because assets disposed of have not been recorded in the fixed asset register / general ledger.
B8: Fixed Assets | C8: RSKFA6 - Risk of misstatement of fixed assets because initial measurement, subsequent measurement and impairment testing of fixed assets have not been done in the manner specified in the financial reporting framework | D8: E | E8: R | F8: V | G8: A | Q8: =D8&$C8 -> ERSKFA6 - Risk of misstatement of fixed assets because initial measurement, subsequent measurement and impairment testing of fixed assets have not been done in the manner specified in the financial reporting framework | R8: =E8&$C8 -> RRSKFA6 - Risk of misstatement of fixed assets because initial measurement, subsequent measurement and impairment testing of fixed assets have not been done in the manner specified in the financial reporting framework | S8: =F8&$C8 -> VRSKFA6 - Risk of misstatement of fixed assets because initial measurement, subsequent measurement and impairment testing of fixed assets have not been done in the manner specified in the financial reporting framework | T8: =G8&$C8 -> ARSKFA6 - Risk of misstatement of fixed assets because initial measurement, subsequent measurement and impairment testing of fixed assets have not been done in the manner specified in the financial reporting framework
B9: Fixed Assets | C9: RSKFA7 - Risk of misstatement of fixed assets because the depreciation method and / or depreciation rate adopted are not in compliance with the applicable statutes | D9: V | E9: A | Q9: =D9&$C9 -> VRSKFA7 - Risk of misstatement of fixed assets because the depreciation method and / or depreciation rate adopted are not in compliance with the applicable statutes | R9: =E9&$C9 -> ARSKFA7 - Risk of misstatement of fixed assets because the depreciation method and / or depreciation rate adopted are not in compliance with the applicable statutes
B11: Cash & Bank | C11: RSKCB1 - Risk of overstatement of Cash balance (Eg: non-existent cash receipts have been recorded, cash payments omited to be recorded etc.) | D11: E | E11: R | F11: V | I11: 4 | J11: E | K11: R | L11: C | M11: V | Q11: =D11&$C11 -> ERSKCB1 - Risk of overstatement of Cash balance (Eg: non-existent cash receipts have been recorded, cash payments omited to be recorded etc.) | R11: =E11&$C11 -> RRSKCB1 - Risk of overstatement of Cash balance (Eg: non-existent cash receipts have been recorded, cash payments omited to be recorded etc.) | S11: =F11&$C11 -> VRSKCB1 - Risk of overstatement of Cash balance (Eg: non-existent cash receipts have been recorded, cash payments omited to be recorded etc.)
B12: Cash & Bank | C12: RSKCB2 - Risk of understatement of Cash balance (Eg: non-existent cash payments have been recorded, cash receipts omited to be recorded etc.) | D12: E | E12: R | F12: V | Q12: =D12&$C12 -> ERSKCB2 - Risk of understatement of Cash balance (Eg: non-existent cash payments have been recorded, cash receipts omited to be recorded etc.) | R12: =E12&$C12 -> RRSKCB2 - Risk of understatement of Cash balance (Eg: non-existent cash payments have been recorded, cash receipts omited to be recorded etc.) | S12: =F12&$C12 -> VRSKCB2 - Risk of understatement of Cash balance (Eg: non-existent cash payments have been recorded, cash receipts omited to be recorded etc.)
B13: Cash & Bank | C13: RSKCB3 - Risk of misstatement of Cash because cash on hand has been misappropriated / stolen. | D13: E | E13: R | Q13: =D13&$C13 -> ERSKCB3 - Risk of misstatement of Cash because cash on hand has been misappropriated / stolen. | R13: =E13&$C13 -> RRSKCB3 - Risk of misstatement of Cash because cash on hand has been misappropriated / stolen.
B14: Cash & Bank | C14: RSKCB4 - Risk of overstatement of bank balance (Eg: non-existent bank receipts have been recorded, bank payments or charges omitted to be recorded etc) | D14: E | E14: R | F14: C | G14: V | Q14: =D14&$C14 -> ERSKCB4 - Risk of overstatement of bank balance (Eg: non-existent bank receipts have been recorded, bank payments or charges omitted to be recorded etc) | R14: =E14&$C14 -> RRSKCB4 - Risk of overstatement of bank balance (Eg: non-existent bank receipts have been recorded, bank payments or charges omitted to be recorded etc) | S14: =F14&$C14 -> C RSKCB4 - Risk of overstatement of bank balance (Eg: non-existent bank receipts have been recorded, bank payments or charges omitted to be recorded etc) | T14: =G14&$C14 -> VRSKCB4 - Risk of overstatement of bank balance (Eg: non-existent bank receipts have been recorded, bank payments or charges omitted to be recorded etc)
B15: Cash & Bank | C15: RSKCB5 - Risk of understatement of bank balance (Eg: non-existent bank payments recorded, bank receipts omitted to be recorded etc) | D15: E | E15: R | F15: C | G15: V | Q15: =D15&$C15 -> ERSKCB5 - Risk of understatement of bank balance (Eg: non-existent bank payments recorded, bank receipts omitted to be recorded etc) | R15: =E15&$C15 -> RRSKCB5 - Risk of understatement of bank balance (Eg: non-existent bank payments recorded, bank receipts omitted to be recorded etc) | S15: =F15&$C15 -> CRSKCB5 - Risk of understatement of bank balance (Eg: non-existent bank payments recorded, bank receipts omitted to be recorded etc) | T15: =G15&$C15 -> VRSKCB5 - Risk of understatement of bank balance (Eg: non-existent bank payments recorded, bank receipts omitted to be recorded etc)
B16: Cash & Bank | C16: RSKCB6 - Risk of understatement of Bank because interest accrued in the bank accounts have not been recorded by the entity. | D16: R | E16: C | F16: V | Q16: =D16&$C16 -> RRSKCB6 - Risk of understatement of Bank because interest accrued in the bank accounts have not been recorded by the entity. | R16: =E16&$C16 -> CRSKCB6 - Risk of understatement of Bank because interest accrued in the bank accounts have not been recorded by the entity. | S16: =F16&$C16 -> VRSKCB6 - Risk of understatement of Bank because interest accrued in the bank accounts have not been recorded by the entity.
B18: Payroll | C18: RSKPAY1 - Risk of misstatement of payroll expense due to recording of incorrect amount as payroll cost (i.e., due to updation of wrong salary cost in the payroll master file). | D18: O | E18: C | F18: A | G18: CO | I18: 6 | J18: O | K18: CL | L18: C | M18: A | N18: CO | O18: PD | Q18: =D18&$C18 -> ORSKPAY1 - Risk of misstatement of payroll expense due to recording of incorrect amount as payroll cost (i.e., due to updation of wrong salary cost in the payroll master file). | R18: =E18&$C18 -> CRSKPAY1 - Risk of misstatement of payroll expense due to recording of incorrect amount as payroll cost (i.e., due to updation of wrong salary cost in the payroll master file). | S18: =F18&$C18 -> ARSKPAY1 - Risk of misstatement of payroll expense due to recording of incorrect amount as payroll cost (i.e., due to updation of wrong salary cost in the payroll master file). | T18: =G18&$C18 -> CORSKPAY1 - Risk of misstatement of payroll expense due to recording of incorrect amount as payroll cost (i.e., due to updation of wrong salary cost in the payroll master file).
B19: Payroll | C19: RSKPAY2 - Risk of misstatement of payroll expense due to recording of payroll cost in the wrong period. | D19: A | E19: CO | Q19: =D19&$C19 -> ARSKPAY2 - Risk of misstatement of payroll expense due to recording of payroll cost in the wrong period. | R19: =E19&$C19 -> CORSKPAY2 - Risk of misstatement of payroll expense due to recording of payroll cost in the wrong period.
B20: Payroll | C20: RSKPAY3 - Risk of understatement of payroll cost because the withheld taxes and other deductions are not recorded (i.e., payroll cost is recorded for net payroll and not gross payroll). | D20: C | E20: A | Q20: =D20&$C20 -> CRSKPAY3 - Risk of understatement of payroll cost because the withheld taxes and other deductions are not recorded (i.e., payroll cost is recorded for net payroll and not gross payroll). | R20: =E20&$C20 -> ARSKPAY3 - Risk of understatement of payroll cost because the withheld taxes and other deductions are not recorded (i.e., payroll cost is recorded for net payroll and not gross payroll).
B21: Payroll | C21: RSKPAY4 - Risk of misstatement of Provident Fund and ESI expense recorded because the statutory rate of contribution applied is incorrect or contribution has not been calculated for all employees due to processing errors. | D21: C | E21: A | Q21: =D21&$C21 -> CRSKPAY4 - Risk of misstatement of Provident Fund and ESI expense recorded because the statutory rate of contribution applied is incorrect or contribution has not been calculated for all employees due to processing errors. | R21: =E21&$C21 -> ARSKPAY4 - Risk of misstatement of Provident Fund and ESI expense recorded because the statutory rate of contribution applied is incorrect or contribution has not been calculated for all employees due to processing errors.
B22: Payroll | C22: RSKPAY5 - Risk of misstatement of leave salary expense and accrual because the leave, salary and other relevant data provided for actuarial valuation is incorrect and disclosures required as per the financial reporting framework are not given | D22: C | E22: A | F22: CL | Q22: =D22&$C22 -> CRSKPAY5 - Risk of misstatement of leave salary expense and accrual because the leave, salary and other relevant data provided for actuarial valuation is incorrect and disclosures required as per the financial reporting framework are not given | R22: =E22&$C22 -> ARSKPAY5 - Risk of misstatement of leave salary expense and accrual because the leave, salary and other relevant data provided for actuarial valuation is incorrect and disclosures required as per the financial reporting framework are not given | S22: =F22&$C22 -> CLRSKPAY5 - Risk of misstatement of leave salary expense and accrual because the leave, salary and other relevant data provided for actuarial valuation is incorrect and disclosures required as per the financial reporting framework are not given
B23: Payroll | C23: RSKPAY6 - Risk that employee costs are not recorded in the correct ledgers according to their nature (direct wages, indirect costs, staff welfare etc) which could impact calculation of production overhead rates and consquently inventory valuation. | D23: CL | E23: P&D | Q23: =D23&$C23 -> CLRSKPAY6 - Risk that employee costs are not recorded in the correct ledgers according to their nature (direct wages, indirect costs, staff welfare etc) which could impact calculation of production overhead rates and consquently inventory valuation. | R23: =E23&$C23 -> P&DRSKPAY6 - Risk that employee costs are not recorded in the correct ledgers according to their nature (direct wages, indirect costs, staff welfare etc) which could impact calculation of production overhead rates and consquently inventory valuation.
B25: Inventory | C25: RSKINV1 - Risk of understatement of Inventory because inventory on hand and inventory received from suppliers are not included in inventory records. | D25: E | E25: R | F25: C | G25: V | I25: 6 | J25: E | K25: R | L25: C | M25: V | N25: A | O25: P&D | Q25: =D25&$C25 -> ERSKINV1 - Risk of understatement of Inventory because inventory on hand and inventory received from suppliers are not included in inventory records. | R25: =E25&$C25 -> RRSKINV1 - Risk of understatement of Inventory because inventory on hand and inventory received from suppliers are not included in inventory records. | S25: =F25&$C25 -> CRSKINV1 - Risk of understatement of Inventory because inventory on hand and inventory received from suppliers are not included in inventory records. | T25: =G25&$C25 -> VRSKINV1 - Risk of understatement of Inventory because inventory on hand and inventory received from suppliers are not included in inventory records.
B26: Inventory | C26: RSKINV2 - Risk of overstatement of Inventory because inventory records include inventory that has been sold to customers / consumed. | D26: E | E26: R | F26: C | Q26: =D26&$C26 -> ERSKINV2 - Risk of overstatement of Inventory because inventory records include inventory that has been sold to customers / consumed. | R26: =E26&$C26 -> RRSKINV2 - Risk of overstatement of Inventory because inventory records include inventory that has been sold to customers / consumed. | S26: =F26&$C26 -> CRSKINV2 - Risk of overstatement of Inventory because inventory records include inventory that has been sold to customers / consumed.
B27: Inventory | C27: RSKINV3 - Risk of overstatement of Inventory because inventory is old, obsolete, damaged, not usable or is saleable at amounts less than that at which it is recorded. | D27: V | E27: A | Q27: =D27&$C27 -> VRSKINV3 - Risk of overstatement of Inventory because inventory is old, obsolete, damaged, not usable or is saleable at amounts less than that at which it is recorded. | R27: =E27&$C27 -> ARSKINV3 - Risk of overstatement of Inventory because inventory is old, obsolete, damaged, not usable or is saleable at amounts less than that at which it is recorded.
B28: Inventory | C28: RSKINV4 - Risk of misstatement of Inventory because the prices used to value inventory and / or the valuation principles and methods used are incorrect and associated material costs and overheads (production and indirect overheads) are not allocated to Finished goods and work in progress on a reasonable basis | D28: V | E28: A | Q28: =D28&$C28 -> VRSKINV4 - Risk of misstatement of Inventory because the prices used to value inventory and / or the valuation principles and methods used are incorrect and associated material costs and overheads (production and indirect overheads) are not allocated to Finished goods and work in progress on a reasonable basis | R28: =E28&$C28 -> ARSKINV4 - Risk of misstatement of Inventory because the prices used to value inventory and / or the valuation principles and methods used are incorrect and associated material costs and overheads (production and indirect overheads) are not allocated to Finished goods and work in progress on a reasonable basis
B29: Inventory | C29: RSKINV5 - Risk that inventory balances are intentionally misstated so as to ensure better working capital borrowing limits | D29: V | E29: A | F29: P&D | Q29: =D29&$C29 -> VRSKINV5 - Risk that inventory balances are intentionally misstated so as to ensure better working capital borrowing limits | R29: =E29&$C29 -> ARSKINV5 - Risk that inventory balances are intentionally misstated so as to ensure better working capital borrowing limits | S29: =F29&$C29 -> P&DRSKINV5 - Risk that inventory balances are intentionally misstated so as to ensure better working capital borrowing limits
B31: Receivables | C31: RSKDRS1 - Risk of misstatement of Accounts receivable because invoices issued and recorded do not relate to valid sales / shipments or because invoices are not recorded at all. | D31: E | E31: R | I31: 5 | J31: E | K31: R | L31: C | M31: V | N31: A | Q31: =D31&$C31 -> ERSKDRS1 - Risk of misstatement of Accounts receivable because invoices issued and recorded do not relate to valid sales / shipments or because invoices are not recorded at all. | R31: =E31&$C31 -> RRSKDRS1 - Risk of misstatement of Accounts receivable because invoices issued and recorded do not relate to valid sales / shipments or because invoices are not recorded at all.
B32: Receivables | C32: RSKDRS2 - Risk of misstatement of Accounts receivable because of errors in the calculation of sales value on the invoice. | D32: R | E32: V | Q32: =D32&$C32 -> RRSKDRS2 - Risk of misstatement of Accounts receivable because of errors in the calculation of sales value on the invoice. | R32: =E32&$C32 -> VRSKDRS2 - Risk of misstatement of Accounts receivable because of errors in the calculation of sales value on the invoice.
B33: Receivables | C33: RSKDRS3 - Risk of misstatement of Accounts receivable because receipts from customers is recorded more than once or are not recorded at all. | D33: E | E33: R | F33: V | G33: C | Q33: =D33&$C33 -> ERSKDRS3 - Risk of misstatement of Accounts receivable because receipts from customers is recorded more than once or are not recorded at all. | R33: =E33&$C33 -> RRSKDRS3 - Risk of misstatement of Accounts receivable because receipts from customers is recorded more than once or are not recorded at all. | S33: =F33&$C33 -> VRSKDRS3 - Risk of misstatement of Accounts receivable because receipts from customers is recorded more than once or are not recorded at all. | T33: =G33&$C33 -> CRSKDRS3 - Risk of misstatement of Accounts receivable because receipts from customers is recorded more than once or are not recorded at all.
B34: Receivables | C34: RSKDRS4 - Risk of overstatement of Accounts receivable because of understatement of allowance for doubtful debts. | D34: R | E34: V | F34: A | Q34: =D34&$C34 -> RRSKDRS4 - Risk of overstatement of Accounts receivable because of understatement of allowance for doubtful debts. | R34: =E34&$C34 -> VRSKDRS4 - Risk of overstatement of Accounts receivable because of understatement of allowance for doubtful debts. | S34: =F34&$C34 -> ARSKDRS4 - Risk of overstatement of Accounts receivable because of understatement of allowance for doubtful debts.
B35: Receivables | C35: RSKDRS5 - Risk of overstatement of bad debts because debtors are written off as bad without proper approvals | D35: E | E35: R | F35: V | Q35: =D35&$C35 -> ERSKDRS5 - Risk of overstatement of bad debts because debtors are written off as bad without proper approvals | R35: =E35&$C35 -> RRSKDRS5 - Risk of overstatement of bad debts because debtors are written off as bad without proper approvals | S35: =F35&$C35 -> VRSKDRS5 - Risk of overstatement of bad debts because debtors are written off as bad without proper approvals
B36: Receivables | C36: RSKDRS6 - Risk that debts due from directors, related parties of the entity are not separately disclosed as per reporting requirements | D36: P&D | Q36: =D36&$C36 -> P&DRSKDRS6 - Risk that debts due from directors, related parties of the entity are not separately disclosed as per reporting requirements
B38: Investments | C38: RSKINMT1-Risk of misstatement of investment in chit funds since payments to chit companies are not correctly accounted in the books of account | D38: E | E38: R | F38: C | G38: V | I38: 6 | J38: E | K38: R | L38: C | M38: V | N38: A | O38: P&D | Q38: =D38&$C38 -> ERSKINMT1-Risk of misstatement of investment in chit funds since payments to chit companies are not correctly accounted in the books of account | R38: =E38&$C38 -> RRSKINMT1-Risk of misstatement of investment in chit funds since payments to chit companies are not correctly accounted in the books of account | S38: =F38&$C38 -> CRSKINMT1-Risk of misstatement of investment in chit funds since payments to chit companies are not correctly accounted in the books of account | T38: =G38&$C38 -> VRSKINMT1-Risk of misstatement of investment in chit funds since payments to chit companies are not correctly accounted in the books of account
B39: Investments | C39: RSKINMT2-Risk of misstatement of investments in shares and mutual funds since amounts invested are not accounted and measured as per the requirements of relevant accounting standards | D39: E | E39: R | F39: V | G39: A | Q39: =D39&$C39 -> ERSKINMT2-Risk of misstatement of investments in shares and mutual funds since amounts invested are not accounted and measured as per the requirements of relevant accounting standards | R39: =E39&$C39 -> RRSKINMT2-Risk of misstatement of investments in shares and mutual funds since amounts invested are not accounted and measured as per the requirements of relevant accounting standards | S39: =F39&$C39 -> VRSKINMT2-Risk of misstatement of investments in shares and mutual funds since amounts invested are not accounted and measured as per the requirements of relevant accounting standards | T39: =G39&$C39 -> ARSKINMT2-Risk of misstatement of investments in shares and mutual funds since amounts invested are not accounted and measured as per the requirements of relevant accounting standards
B40: Investments | C40: RSKINMT3-Risk that investments made by the company are not appropriately classified and disclosed in the financial statements | D40: V | E40: P&D | Q40: =D40&$C40 -> VRSKINMT3-Risk that investments made by the company are not appropriately classified and disclosed in the financial statements | R40: =E40&$C40 -> P&DRSKINMT3-Risk that investments made by the company are not appropriately classified and disclosed in the financial statements
B42: Equity | C42: RSKEQ1 - Risk of understatement of equity because shares issued during the year are not recorded in the general ledger. | D42: E | E42: R | F42: V | I42: 4 | J42: E | K42: R | M42: V | N42: A | Q42: =D42&$C42 -> ERSKEQ1 - Risk of understatement of equity because shares issued during the year are not recorded in the general ledger. | R42: =E42&$C42 -> RRSKEQ1 - Risk of understatement of equity because shares issued during the year are not recorded in the general ledger. | S42: =F42&$C42 -> VRSKEQ1 - Risk of understatement of equity because shares issued during the year are not recorded in the general ledger.
B43: Equity | C43: RSKEQ2 - Risk of understatement of equity because mandatory transfer to reserves on declaration / payment of dividend is not recorded. | D43: E | E43: R | F43: V | Q43: =D43&$C43 -> ERSKEQ2 - Risk of understatement of equity because mandatory transfer to reserves on declaration / payment of dividend is not recorded. | R43: =E43&$C43 -> RRSKEQ2 - Risk of understatement of equity because mandatory transfer to reserves on declaration / payment of dividend is not recorded. | S43: =F43&$C43 -> VRSKEQ2 - Risk of understatement of equity because mandatory transfer to reserves on declaration / payment of dividend is not recorded.
B44: Equity | C44: RSKEQ3 - Risk of overstatement of equity because dividend declared on share capital plus corporate dividend tax are not recorded in the general ledger. | D44: V | E44: A | Q44: =D44&$C44 -> VRSKEQ3 - Risk of overstatement of equity because dividend declared on share capital plus corporate dividend tax are not recorded in the general ledger. | R44: =E44&$C44 -> ARSKEQ3 - Risk of overstatement of equity because dividend declared on share capital plus corporate dividend tax are not recorded in the general ledger.
B46: Debt | C46: RSKDBT1 - Risk of overstatement of recorded debt (Eg: Due to non recording of payments, personal loans of directors/partners accounted in the firm's books etc) | D46: E | E46: O | F46: C | I46: 6 | J46: E | K46: O | L46: C | M46: V | N46: A | O46: P&D | Q46: =D46&$C46 -> ERSKDBT1 - Risk of overstatement of recorded debt (Eg: Due to non recording of payments, personal loans of directors/partners accounted in the firm's books etc) | R46: =E46&$C46 -> ORSKDBT1 - Risk of overstatement of recorded debt (Eg: Due to non recording of payments, personal loans of directors/partners accounted in the firm's books etc) | S46: =F46&$C46 -> CRSKDBT1 - Risk of overstatement of recorded debt (Eg: Due to non recording of payments, personal loans of directors/partners accounted in the firm's books etc)
B47: Debt | C47: RSKDBT3 - Risk of non compliance with the terms of the loan | D47: O | Q47: =D47&$C47 -> ORSKDBT3 - Risk of non compliance with the terms of the loan
B48: Debt | C48: RSKDBT4 - Risk of misstatement of loan balance and interest expense due to non recording/incorrect recording of interest expense | D48: O | E48: C | F48: V | G48: A | Q48: =D48&$C48 -> ORSKDBT4 - Risk of misstatement of loan balance and interest expense due to non recording/incorrect recording of interest expense | R48: =E48&$C48 -> CRSKDBT4 - Risk of misstatement of loan balance and interest expense due to non recording/incorrect recording of interest expense | S48: =F48&$C48 -> VRSKDBT4 - Risk of misstatement of loan balance and interest expense due to non recording/incorrect recording of interest expense | T48: =G48&$C48 -> ARSKDBT4 - Risk of misstatement of loan balance and interest expense due to non recording/incorrect recording of interest expense
B49: Debt | C49: RSKDBT5 - Risk of erroneous classification of loan outstanding balance and interest expense in the financial statements | D49: P&D | E49: A | Q49: =D49&$C49 -> P&DRSKDBT5 - Risk of erroneous classification of loan outstanding balance and interest expense in the financial statements | R49: =E49&$C49 -> ARSKDBT5 - Risk of erroneous classification of loan outstanding balance and interest expense in the financial statements
B50: Debt | C50: RSKDBT6 - Risk of failure to disclose or erroneous classification of guarantees and other non fund based financial arrangements in the financial statements | D50: P&D | E50: A | Q50: =D50&$C50 -> P&DRSKDBT6 - Risk of failure to disclose or erroneous classification of guarantees and other non fund based financial arrangements in the financial statements | R50: =E50&$C50 -> ARSKDBT6 - Risk of failure to disclose or erroneous classification of guarantees and other non fund based financial arrangements in the financial statements
B51: Debt | C51: RSKDBT7 - Risk of incomplete disclosure of particulars with respect to loans such as charges, security details etc | D51: P&D | Q51: =D51&$C51 -> P&DRSKDBT7 - Risk of incomplete disclosure of particulars with respect to loans such as charges, security details etc
B53: Accounts payable | C53: RSKCL1 - Risk of overstatement of Accounts payable because transactions recorded as accounts payable are non-existant or fictitious. | D53: E | E53: O | F53: C | I53: 6 | J53: E | K53: O | L53: C | M53: V | N53: A | O53: P&D | Q53: =D53&$C53 -> ERSKCL1 - Risk of overstatement of Accounts payable because transactions recorded as accounts payable are non-existant or fictitious. | R53: =E53&$C53 -> ORSKCL1 - Risk of overstatement of Accounts payable because transactions recorded as accounts payable are non-existant or fictitious. | S53: =F53&$C53 -> CRSKCL1 - Risk of overstatement of Accounts payable because transactions recorded as accounts payable are non-existant or fictitious.
B54: Accounts payable | C54: RSKCL2 - Risk of understatement of Accounts payable because transactions resulting in accounts payable are not recorded. | D54: O | E54: C | F54: V | Q54: =D54&$C54 -> ORSKCL2 - Risk of understatement of Accounts payable because transactions resulting in accounts payable are not recorded. | R54: =E54&$C54 -> CRSKCL2 - Risk of understatement of Accounts payable because transactions resulting in accounts payable are not recorded. | S54: =F54&$C54 -> VRSKCL2 - Risk of understatement of Accounts payable because transactions resulting in accounts payable are not recorded.
B55: Accounts payable | C55: RSKCL3 - Risk of overstatement of Accounts payable because payments to creditors are not recorded or are not netted off with outstanding payable balance | D55: O | E55: C | F55: A | Q55: =D55&$C55 -> ORSKCL3 - Risk of overstatement of Accounts payable because payments to creditors are not recorded or are not netted off with outstanding payable balance | R55: =E55&$C55 -> CRSKCL3 - Risk of overstatement of Accounts payable because payments to creditors are not recorded or are not netted off with outstanding payable balance | S55: =F55&$C55 -> ARSKCL3 - Risk of overstatement of Accounts payable because payments to creditors are not recorded or are not netted off with outstanding payable balance
B56: Accounts payable | C56: RSKCL4 - Risk of misstatement of foreign supplier balances because such balances are not restated as on the balance sheet date as specified in the financial reporting framework | D56: O | E56: V | Q56: =D56&$C56 -> ORSKCL4 - Risk of misstatement of foreign supplier balances because such balances are not restated as on the balance sheet date as specified in the financial reporting framework | R56: =E56&$C56 -> VRSKCL4 - Risk of misstatement of foreign supplier balances because such balances are not restated as on the balance sheet date as specified in the financial reporting framework
B57: Accounts payable | C57: RSKCL5 - Risk of misstatement of supplier balances because advances made to suppliers for supply of goods/services may end up being irrecoverable if the party does not honour transaction | D57: O | E57: V | Q57: =D57&$C57 -> ORSKCL5 - Risk of misstatement of supplier balances because advances made to suppliers for supply of goods/services may end up being irrecoverable if the party does not honour transaction | R57: =E57&$C57 -> VRSKCL5 - Risk of misstatement of supplier balances because advances made to suppliers for supply of goods/services may end up being irrecoverable if the party does not honour transaction
B58: Accounts payable | C58: RSKCL6 - Risk of misstatement of supplier balances because amounts outstanding to MSME creditors are not appropriately classified and disclosed | D58: O | E58: A | F58: P&D | Q58: =D58&$C58 -> ORSKCL6 - Risk of misstatement of supplier balances because amounts outstanding to MSME creditors are not appropriately classified and disclosed | R58: =E58&$C58 -> ARSKCL6 - Risk of misstatement of supplier balances because amounts outstanding to MSME creditors are not appropriately classified and disclosed | S58: =F58&$C58 -> P&DRSKCL6 - Risk of misstatement of supplier balances because amounts outstanding to MSME creditors are not appropriately classified and disclosed
B60: Expenses payable | C60: RSKEP1 - Risk of misstatement of expenses payable because accrued expenses are not appropriately accounted and classified | D60: E | E60: O | F60: C | G60: V | H60: A | I60: 6 | J60: E | K60: O | L60: C | M60: V | N60: A | O60: CO | Q60: =D60&$C60 -> ERSKEP1 - Risk of misstatement of expenses payable because accrued expenses are not appropriately accounted and classified | R60: =E60&$C60 -> ORSKEP1 - Risk of misstatement of expenses payable because accrued expenses are not appropriately accounted and classified | S60: =F60&$C60 -> CRSKEP1 - Risk of misstatement of expenses payable because accrued expenses are not appropriately accounted and classified | T60: =G60&$C60 -> VRSKEP1 - Risk of misstatement of expenses payable because accrued expenses are not appropriately accounted and classified | U60: =H60&$C60 -> ARSKEP1 - Risk of misstatement of expenses payable because accrued expenses are not appropriately accounted and classified
B61: Expenses payable | C61: RSKEP2 - Risk of misstatement of expenses payable because expenses payable to staff are not correctly accounted and appropriately classified | D61: E | E61: O | F61: C | G61: V | H61: A | Q61: =D61&$C61 -> ERSKEP2 - Risk of misstatement of expenses payable because expenses payable to staff are not correctly accounted and appropriately classified | R61: =E61&$C61 -> ORSKEP2 - Risk of misstatement of expenses payable because expenses payable to staff are not correctly accounted and appropriately classified | S61: =F61&$C61 -> CRSKEP2 - Risk of misstatement of expenses payable because expenses payable to staff are not correctly accounted and appropriately classified | T61: =G61&$C61 -> VRSKEP2 - Risk of misstatement of expenses payable because expenses payable to staff are not correctly accounted and appropriately classified | U61: =H61&$C61 -> ARSKEP2 - Risk of misstatement of expenses payable because expenses payable to staff are not correctly accounted and appropriately classified
B63: Statutory Payables | C63: RSKSP1 - Risk of misstatement of statutory liabilities because the liabilities are not calculated as per the applicable statutory provisions | D63: E | E63: O | F63: V | G63: CO | H63: A | Q63: =D63&$C63 -> ERSKSP1 - Risk of misstatement of statutory liabilities because the liabilities are not calculated as per the applicable statutory provisions | R63: =E63&$C63 -> ORSKSP1 - Risk of misstatement of statutory liabilities because the liabilities are not calculated as per the applicable statutory provisions | S63: =F63&$C63 -> VRSKSP1 - Risk of misstatement of statutory liabilities because the liabilities are not calculated as per the applicable statutory provisions | T63: =G63&$C63 -> CORSKSP1 - Risk of misstatement of statutory liabilities because the liabilities are not calculated as per the applicable statutory provisions | U63: =H63&$C63 -> ARSKSP1 - Risk of misstatement of statutory liabilities because the liabilities are not calculated as per the applicable statutory provisions
B64: Statutory Payables | C64: RSKSP2 - Risk of misstatement of statutory liabilities because the applicable rates are not applied consistently through out the period under audit | D64: O | E64: C | F64: V | I64: 4 | K64: O | L64: C | M64: V | O64: CO | Q64: =D64&$C64 -> ORSKSP2 - Risk of misstatement of statutory liabilities because the applicable rates are not applied consistently through out the period under audit | R64: =E64&$C64 -> CRSKSP2 - Risk of misstatement of statutory liabilities because the applicable rates are not applied consistently through out the period under audit | S64: =F64&$C64 -> VRSKSP2 - Risk of misstatement of statutory liabilities because the applicable rates are not applied consistently through out the period under audit
B65: Statutory Payables | C65: RSKSP3 - Risk of misstatement of statutory liabilities because the statutory liabilities are not remitted within the applicable due dates | D65: O | E65: C | F65: CO | Q65: =D65&$C65 -> ORSKSP3 - Risk of misstatement of statutory liabilities because the statutory liabilities are not remitted within the applicable due dates | R65: =E65&$C65 -> CRSKSP3 - Risk of misstatement of statutory liabilities because the statutory liabilities are not remitted within the applicable due dates | S65: =F65&$C65 -> CORSKSP3 - Risk of misstatement of statutory liabilities because the statutory liabilities are not remitted within the applicable due dates
B66: Statutory Payables | C66: RSKSP4 - Risk of misstatement of statutory liabilities because the returns are incorrectly filed or not filed at all | D66: O | E66: C | Q66: =D66&$C66 -> ORSKSP4 - Risk of misstatement of statutory liabilities because the returns are incorrectly filed or not filed at all | R66: =E66&$C66 -> CRSKSP4 - Risk of misstatement of statutory liabilities because the returns are incorrectly filed or not filed at all
B68: Loans & advances | C68: RSKLA1 - Risk of understatement of Prepaid expense because prepaid is not recognised for payments in respect of which services have not been received and such payments are wrongly classified as expense. | D68: E | E68: R | F68: C | G68: V | H68: A | I68: 6 | J68: E | K68: R | L68: C | M68: V | N68: A | O68: P&D | Q68: =D68&$C68 -> ERSKLA1 - Risk of understatement of Prepaid expense because prepaid is not recognised for payments in respect of which services have not been received and such payments are wrongly classified as expense. | R68: =E68&$C68 -> RRSKLA1 - Risk of understatement of Prepaid expense because prepaid is not recognised for payments in respect of which services have not been received and such payments are wrongly classified as expense. | S68: =F68&$C68 -> CRSKLA1 - Risk of understatement of Prepaid expense because prepaid is not recognised for payments in respect of which services have not been received and such payments are wrongly classified as expense. | T68: =G68&$C68 -> VRSKLA1 - Risk of understatement of Prepaid expense because prepaid is not recognised for payments in respect of which services have not been received and such payments are wrongly classified as expense. | U68: =H68&$C68 -> ARSKLA1 - Risk of understatement of Prepaid expense because prepaid is not recognised for payments in respect of which services have not been received and such payments are wrongly classified as expense.
B69: Loans & advances | C69: RSKLA2 - Risk of overstatement of Prepaid expense because amounts included in prepaid expense relate to fictitious or unauthorised transction. | D69: E | E69: R | F69: C | Q69: =D69&$C69 -> ERSKLA2 - Risk of overstatement of Prepaid expense because amounts included in prepaid expense relate to fictitious or unauthorised transction. | R69: =E69&$C69 -> RRSKLA2 - Risk of overstatement of Prepaid expense because amounts included in prepaid expense relate to fictitious or unauthorised transction. | S69: =F69&$C69 -> CRSKLA2 - Risk of overstatement of Prepaid expense because amounts included in prepaid expense relate to fictitious or unauthorised transction.
B70: Loans & advances | C70: RSKLA3 - Risk of misstatement of Staff advances because the balance in staff advance account pertain to employees who have left the organisation | D70: E | E70: R | F70: V | Q70: =D70&$C70 -> ERSKLA3 - Risk of misstatement of Staff advances because the balance in staff advance account pertain to employees who have left the organisation | R70: =E70&$C70 -> RRSKLA3 - Risk of misstatement of Staff advances because the balance in staff advance account pertain to employees who have left the organisation | S70: =F70&$C70 -> VRSKLA3 - Risk of misstatement of Staff advances because the balance in staff advance account pertain to employees who have left the organisation
B71: Loans & advances | C71: RSKLA4 - Risk of misstatement of Deposits because the the recorded deposits are fictitious or non-recoverable/doubtful or without proper supportings | D71: E | E71: R | F71: C | G71: V | Q71: =D71&$C71 -> ERSKLA4 - Risk of misstatement of Deposits because the the recorded deposits are fictitious or non-recoverable/doubtful or without proper supportings | R71: =E71&$C71 -> RRSKLA4 - Risk of misstatement of Deposits because the the recorded deposits are fictitious or non-recoverable/doubtful or without proper supportings | S71: =F71&$C71 -> CRSKLA4 - Risk of misstatement of Deposits because the the recorded deposits are fictitious or non-recoverable/doubtful or without proper supportings | T71: =G71&$C71 -> VRSKLA4 - Risk of misstatement of Deposits because the the recorded deposits are fictitious or non-recoverable/doubtful or without proper supportings
B72: Loans & advances | C72: RSKLA5 - Risk of misstatement of Loans & advances or Deposits because the required classification into current and non current as required by the framework is not done | D72: P&D | E72: A | Q72: =D72&$C72 -> P&DRSKLA5 - Risk of misstatement of Loans & advances or Deposits because the required classification into current and non current as required by the framework is not done | R72: =E72&$C72 -> ARSKLA5 - Risk of misstatement of Loans & advances or Deposits because the required classification into current and non current as required by the framework is not done
B73: Loans & advances | C73: RSKLA6 - Risk of misstatement of Loans & advances or Deposits because doubtful deposits are not adequately proviided for | D73: P&D | E73: A | Q73: =D73&$C73 -> P&DRSKLA6 - Risk of misstatement of Loans & advances or Deposits because doubtful deposits are not adequately proviided for | R73: =E73&$C73 -> ARSKLA6 - Risk of misstatement of Loans & advances or Deposits because doubtful deposits are not adequately proviided for
B75: Revenue | C75: RSKRE1 - Risk of overstatement of revenue because invoices issued and recorded do not relate to valid sales / shipments. | D75: O | I75: 4 | J75: O | K75: C | L75: A | M75: CO | Q75: =D75&$C75 -> ORSKRE1 - Risk of overstatement of revenue because invoices issued and recorded do not relate to valid sales / shipments.
B76: Revenue | C76: RSKRE2 - Risk of understatement of revenue because invoices issued to customer are not recorded. | D76: O | E76: C | Q76: =D76&$C76 -> ORSKRE2 - Risk of understatement of revenue because invoices issued to customer are not recorded. | R76: =E76&$C76 -> CRSKRE2 - Risk of understatement of revenue because invoices issued to customer are not recorded.
B77: Revenue | C77: RSKRE3 - Risk of misstatement of revenue because sale price is not agreeing with the approved price list. | D77: A | Q77: =D77&$C77 -> ARSKRE3 - Risk of misstatement of revenue because sale price is not agreeing with the approved price list.
B78: Revenue | C78: RSKRE4 - Risk of misstatement of revenue because of errors in the calculation of sales value on the invoice. | D78: A | Q78: =D78&$C78 -> ARSKRE4 - Risk of misstatement of revenue because of errors in the calculation of sales value on the invoice.
B79: Revenue | C79: RSKRE5 - Risk of misstatement of revenue because discounts from sale price shown on the invoice are not calculated in accordance with the approved discount rates. | D79: A | Q79: =D79&$C79 -> ARSKRE5 - Risk of misstatement of revenue because discounts from sale price shown on the invoice are not calculated in accordance with the approved discount rates.
B80: Revenue | C80: RSKRE6 - Risk of misstatement of revenue because credit notes issued and recorded do not relate to valid sales returns. | D80: O | Q80: =D80&$C80 -> ORSKRE6 - Risk of misstatement of revenue because credit notes issued and recorded do not relate to valid sales returns.
B81: Revenue | C81: RSKRE7 - Risk of misstatement of revenue due to recording in the incorrect period | D81: CO | Q81: =D81&$C81 -> CORSKRE7 - Risk of misstatement of revenue due to recording in the incorrect period
B83: Provisions | C83: RSKPROV1 - Risk of misstatement of accrual for gratuity liability at the balance sheet date because the salary, period of service, and other relevant data provided by the entity for actuarial valuation is incorrect. | D83: E | E83: O | F83: V | I83: 5 | J83: E | K83: O | L83: C | M83: V | N83: A | Q83: =D83&$C83 -> ERSKPROV1 - Risk of misstatement of accrual for gratuity liability at the balance sheet date because the salary, period of service, and other relevant data provided by the entity for actuarial valuation is incorrect. | R83: =E83&$C83 -> ORSKPROV1 - Risk of misstatement of accrual for gratuity liability at the balance sheet date because the salary, period of service, and other relevant data provided by the entity for actuarial valuation is incorrect. | S83: =F83&$C83 -> VRSKPROV1 - Risk of misstatement of accrual for gratuity liability at the balance sheet date because the salary, period of service, and other relevant data provided by the entity for actuarial valuation is incorrect.
B84: Provisions | C84: RSKPROV2 - Risk of misstatement of provision for doubtful balances because of doubtful balances are not properly estimated/ascertained | D84: E | E84: V | F84: A | Q84: =D84&$C84 -> ERSKPROV2 - Risk of misstatement of provision for doubtful balances because of doubtful balances are not properly estimated/ascertained | R84: =E84&$C84 -> VRSKPROV2 - Risk of misstatement of provision for doubtful balances because of doubtful balances are not properly estimated/ascertained | S84: =F84&$C84 -> ARSKPROV2 - Risk of misstatement of provision for doubtful balances because of doubtful balances are not properly estimated/ascertained
B85: Provisions | C85: RSKPROV3 - Risk of understatement of expenses and provision balance as accruals of fabricator incentive and product warranties are not appropriately accounted | D85: O | E85: C | F85: V | G85: A | Q85: =D85&$C85 -> ORSKPROV3 - Risk of understatement of expenses and provision balance as accruals of fabricator incentive and product warranties are not appropriately accounted | R85: =E85&$C85 -> CRSKPROV3 - Risk of understatement of expenses and provision balance as accruals of fabricator incentive and product warranties are not appropriately accounted | S85: =F85&$C85 -> VRSKPROV3 - Risk of understatement of expenses and provision balance as accruals of fabricator incentive and product warranties are not appropriately accounted | T85: =G85&$C85 -> ARSKPROV3 - Risk of understatement of expenses and provision balance as accruals of fabricator incentive and product warranties are not appropriately accounted
B87: Expenses (Including purchases) | C87: RSKEXP1 - Risk of overstatement of discounts given to distributors / dealers because the transactions recorded in the general ledger are fictitious or unauthorised. | D87: O | I87: 4 | J87: O | K87: C | L87: A | M87: CL | Q87: =D87&$C87 -> ORSKEXP1 - Risk of overstatement of discounts given to distributors / dealers because the transactions recorded in the general ledger are fictitious or unauthorised.
B88: Expenses (Including purchases) | C88: RSKEXP2 - Risk of mistatement of advertisement expenses because the transactions recorded in the general ledger are fictitious or unauthorised or the same are not recorded at all | D88: O | E88: C | Q88: =D88&$C88 -> ORSKEXP2 - Risk of mistatement of advertisement expenses because the transactions recorded in the general ledger are fictitious or unauthorised or the same are not recorded at all | R88: =E88&$C88 -> CRSKEXP2 - Risk of mistatement of advertisement expenses because the transactions recorded in the general ledger are fictitious or unauthorised or the same are not recorded at all
B89: Expenses (Including purchases) | C89: RSKEXP3 - Risk of mistatement of finance expenses because the transactions recorded in the general ledger are fictitious or unauthorised or the same are not recorded at all | D89: O | E89: C | F89: A | Q89: =D89&$C89 -> ORSKEXP3 - Risk of mistatement of finance expenses because the transactions recorded in the general ledger are fictitious or unauthorised or the same are not recorded at all | R89: =E89&$C89 -> CRSKEXP3 - Risk of mistatement of finance expenses because the transactions recorded in the general ledger are fictitious or unauthorised or the same are not recorded at all | S89: =F89&$C89 -> ARSKEXP3 - Risk of mistatement of finance expenses because the transactions recorded in the general ledger are fictitious or unauthorised or the same are not recorded at all
B90: Expenses (Including purchases) | C90: RSKEXP4 - Risk of mistatement of depreciation expenses because the transactions recorded in the general ledger are fictitious or unauthorised or the same are not recorded at all | D90: O | E90: C | Q90: =D90&$C90 -> ORSKEXP4 - Risk of mistatement of depreciation expenses because the transactions recorded in the general ledger are fictitious or unauthorised or the same are not recorded at all | R90: =E90&$C90 -> CRSKEXP4 - Risk of mistatement of depreciation expenses because the transactions recorded in the general ledger are fictitious or unauthorised or the same are not recorded at all
B91: Expenses (Including purchases) | C91: RSKEXP5 - Risk of mistatement of Bad debts expenses because the transactions recorded in the general ledger are fictitious or unauthorised or the same are not recorded at all | D91: O | E91: C | Q91: =D91&$C91 -> ORSKEXP5 - Risk of mistatement of Bad debts expenses because the transactions recorded in the general ledger are fictitious or unauthorised or the same are not recorded at all | R91: =E91&$C91 -> CRSKEXP5 - Risk of mistatement of Bad debts expenses because the transactions recorded in the general ledger are fictitious or unauthorised or the same are not recorded at all
B92: Expenses (Including purchases) | C92: RSKEXP6 - Risk of mistatement of Administration, establishment expenses because the transactions recorded in the general ledger are fictitious or unauthorised or the same are not recorded at all | D92: O | E92: C | F92: A | G92: CL | Q92: =D92&$C92 -> ORSKEXP6 - Risk of mistatement of Administration, establishment expenses because the transactions recorded in the general ledger are fictitious or unauthorised or the same are not recorded at all | R92: =E92&$C92 -> CRSKEXP6 - Risk of mistatement of Administration, establishment expenses because the transactions recorded in the general ledger are fictitious or unauthorised or the same are not recorded at all | S92: =F92&$C92 -> ARSKEXP6 - Risk of mistatement of Administration, establishment expenses because the transactions recorded in the general ledger are fictitious or unauthorised or the same are not recorded at all | T92: =G92&$C92 -> CLRSKEXP6 - Risk of mistatement of Administration, establishment expenses because the transactions recorded in the general ledger are fictitious or unauthorised or the same are not recorded at all

Sheet ROMM & FAP summary - MCOTABD
B2: Identified ROMM at Financial Statement Level | H2: SA 330-Para A1
B3: WP Reference | C3: Risks Identified | D3: Resulting in FS level risk | E3: Whether Pervasive? | F3: Management Plans to address Risk | G3: Further Audit Procedures Planned / Remarks of Auditor | H3: Application and Other Explanatory Material
B4: [2020.01 Understanding the entity] | C4: The relationships with suppliers and customers are generally cordial. Rawmaterial imported is supplied against advances paid to suppliers which is not against any contract and therefore there is risk that the party may not honour the purchase transaction | D4: Yes | E4: Yes | F4: The management relies on the long term association they have had with the supplier and is of the opinion that this risk is not material. Further, advance paid at the time of placing an import order is only 15% of the import value after which the supplier starts manufacturing the required batch. Further the entity's agent who facilitates the import transactions acts as an extended arm of the entity and effectively coordinates the transaction. | G4: SPCL5 - Verifying terms of contract with major suppliers SPCL6 - Subsequent settlement testing | H4: Overall Responses (Ref: Para. 5)
B5: [2020.01 Understanding the entity] | C5: Rule 3 of Companies Accounts Rules becomes applicable from 01-04-2023.However rule 11(g) of Companies (Audit and Auditors)Rules becomes applicable from 01-04-2022. | F5: Accounting softwares used by entity namely Tallyprime and SAP having audit trial feature.
B6: [2020.02 Understanding the internal control] | C6: TCWG may inadvertently encroach on the roles and responsibilities of operational management, leading to confusion, overlapping duties, or undermining the authority of senior personnel. This can cause friction within the management team, reducing efficiency and effectiveness in decision-making processes. | D6: Yes | E6: Yes | F6: TCWG has delegated certain operational responsibilities to senior management, empowering them to make decisions within their areas of expertise. This Fosters a culture of trust and accountability, allowing senior personnel to lead effectively while TCWG focuses on strategic governance. | G6: It was explained that the entity is in the process of corporatising its operations and accordingly there are structural changes happening. The present involvement of TCWG in operations was warranted since the entity reported losses in the year 2022-23 and the directors took a call to take part more in the operational activities in order to tide over the situation and steady the ship. It was informed that their involvement in the operations will be brought down going forward.
B7: [2020.02 Understanding the internal control] | C7: Absence of a formal documented risk assessment process would mean that risks may not be identified or managed effectively, leading to unforeseen issues that could impact the organization’s performance and stability. | D7: Yes | E7: Yes | F7: Even though the risk assessment process at the entity is not maintained in a documented form, they have good systems and practices in place and are generally compliant with applicable laws and regulations. Further, as per the provisions of Companies act, an "external" internal auditor has been appointed by the entity and the entity is planning to move to a risk based internal audit approach this year the scope of which is being finalised. Iit is expected that a formal documented risk assessment process with risk rankings and matrices will be introduced as part of the same | G7: The entity has the capability and resources to appropriately identify, assess and responds to risks as and when they occur even though such process is not documented or formal. Based on our risk assessment process, we observed that the entity has in place adequate controls to respond to risks at business level, FS level and MCOTABD level. The results of the same are given in the respective working papers FAPFS3 - Monitoring of work FAPFS4 - Unpredictable elements FAPFS5 - Audit procedures to obtain persuasive audit evidence
B8: [2020.02 Understanding the internal control] | C8: Non standard journal entries may be used to misrepresent books of account by artificially overstanding or understanding account balances | D8: Yes | E8: No | F8: There is proper control over passing of non standard journal entries in that such rights are limited to select individuals within the organisation | G8: Non standard journal entries are checked during ledger scrutiny FAPFS7 - Journal entry testing
B9: [2020.02 Understanding the internal control] | C9: Control activities at the entity including Authorisation matrices, segregation etc are not documented. | D9: Yes | E9: Yes | F9: It is ensured that eventhough the activities are not documented, there is an in principle system at the entity to ensure that the same are appropriately being followed. Further, as per the provisions of Companies act, an "external" internal auditor has been appointed by the entity and the entity is planning to move to a risk based internal audit approach this year the scope of which is being finalised. Iit is expected that a formal documented risk assessment process with risk rankings and related control activities will be introduced as part of the same | G9: Based on our risk assessment process, we observed that the entity has in place adequate controls to respond to risks at business level, FS level and MCOTABD level. The results of the same are given in the respective working papers FAPFS1 - Engagement team selection FAPFS2 - Firm's QC policy FAPFS3 - Monitoring of work FAPFS4 - Unpredictable elements FAPFS5 - Audit procedures to obtain persuasive audit evidence FAPFS6 - Results of audit procedures from prior years
B12: ROMM and FAP at MCOTABD Level (For details - Refer ensuing sheets)
F13: Assertions Addressed
B14: Account Balance | C14: Risks Identified | D14: Assertions affected | E14: Type of risk | F14: Control testing | G14: Substantive testing
B15: Fixed Assets | C15: RSKFA1 - Risk of understatement of fixed assets because assets acquired by the entity are not recorded. | D15: R, C, V | E15: Normal | F15: CACL5 - Payment approval | G15: SPFA8 - GSTR2A verification for additions
F16: CACB2 - Monthly bank reco testing | G16: SPFA2 - Additions vouching
G17: SPFA3 - Physical verification procedures
G18: SPCL2 - Creditors balance confirmation
G19: SPCB2 - Bank reconciliation checking
B20: Fixed Assets | C20: RSKFA2 - Risk of understatement of fixed assets because assets in use and still owned by the entity have been wrongly recorded as disposed. | D20: E, R, C, V | E20: Normal | F20: Nil | G20: SPFA1 - Checking OB carried forward
G21: SPFA3 - Physical verification procedures
G22: SPFA9 - Checking GSTRs for asset sale
B23: Fixed Assets | C23: RSKFA3 - Risk of understatement of fixed assets because fixed assets purchased have been expensed and not capitalised. | D23: E, R, V, A | E23: Normal | F23: CAFA3 - Checking asset purchase requisitions | G23: SPFA6 - Repairs & maint ledger scrutiny
F24: CAFA4 - Asset PO verification
F25: CAFA5 - Asset invoice approval
B26: Fixed Assets | C26: RSKFA4 - Risk of overstatement of fixed assets because repairs and maintenance expenses have been incorrectly capitalised as fixed assets. | D26: E, R, V, A | E26: Normal | F26: CAFA5 - Asset invoice approval | G26: SPFA8 - GSTR2A verification for additions
F27: CAFA9 - FA number tagging | G27: SPFA6 - Repairs & maint ledger scrutiny
G28: SPFA10 - Review of CWIP ledger & capitalisation
B29: Fixed Assets | C29: RSKFA5 - Risk of overstatement of fixed assets because assets disposed of have not been recorded in the fixed asset register / general ledger. | D29: E, R | E29: Normal | F29: CAFA9 - FA number tagging | G29: SPFA1 - Checking OB carried forward
G30: SPFA3 - Physical verification procedures
G31: SPFA4 - Testing asset disposals
G32: SPFA9 - Checking GSTRs for asset sale
B33: Fixed Assets | C33: RSKFA6 - Risk of misstatement of fixed assets because initial measurement, subsequent measurement and impairment testing of fixed assets have not been done in the manner specified in the financial reporting framework | D33: E, R, V, A | E33: Normal | F33: CAFA5 - Asset invoice approval | G33: SPFA1 - Checking OB carried forward
G34: SPFA3 - Physical verification procedures
G35: SPFA9 - Checking GSTRs for asset sale
G36: SPFA7 - Impairment testing
B37: Fixed Assets | C37: RSKFA7 - Risk of misstatement of fixed assets because the depreciation method and / or depreciation rate adopted are not in compliance with the applicable statutes | D37: V, A | E37: Normal | F37: Nil | G37: SPFA5 - Depreciation recomputation
G38: SPFA11 - Cross checking with Winman
B39: Cash & Bank | C39: RSKCB1 - Risk of overstatement of Cash balance (Eg: non-existent cash receipts have been recorded, cash payments omited to be recorded etc.) | D39: E, R, V | E39: Normal | F39: CACB1 - Periodic physical verification of cash | G39: SPCB1 - Cash physical verification on BS date
G40: SPCB5 - Physical verification on date other than BS date
B41: Cash & Bank | C41: RSKCB2 - Risk of understatement of Cash balance (Eg: non-existent cash payments have been recorded, cash receipts omited to be recorded etc.) | D41: E, R, V | E41: Normal | F41: CACB1 - Periodic physical verification of cash | G41: SPCB1 - Cash physical verification on BS date
G42: SPCB5 - Physical verification on date other than BS date
B43: Cash & Bank | C43: RSKCB3 - Risk of misstatement of Cash because cash on hand has been misappropriated / stolen. | D43: E, R | E43: Significant | F43: CACB1 - Periodic physical verification of cash | G43: SPCB1 - Cash physical verification on BS date
F44: CACB5 - Cash is kept under lock & key | G44: SPCB5 - Physical verification on date other than BS date
G45: SPCB4 - Whether cash is kept under lock & key
B46: Cash & Bank | C46: RSKCB4 - Risk of overstatement of bank balance (Eg: non-existent bank receipts have been recorded, bank payments or charges omitted to be recorded etc) | D46: E, R, C ,V | E46: Normal | F46: CACB2 - Monthly bank reco testing | G46: SPCB2 - Bank reconciliation checking
F47: CACB3 - Bank confirmation testing | G47: SPCB3 - Bank confirmation testing
F48: CACB4 - Checking BoD minutes
B49: Cash & Bank | C49: RSKCB5 - Risk of understatement of bank balance (Eg: non-existent bank payments recorded, bank receipts omitted to be recorded etc) | D49: E, R, C, V | E49: Normal | F49: CACB2 - Monthly bank reco testing | G49: SPCB2 - Bank reconciliation checking
F50: CACB3 - Bank confirmation testing | G50: SPCB3 - Bank confirmation testing
F51: CACB4 - Checking BoD minutes
B52: Cash & Bank | C52: RSKCB6 - Risk of understatement of Bank because interest accrued in the bank accounts have not been recorded by the entity. | D52: R, C, V | E52: Normal | F52: CACB2 - Monthly bank reco testing | G52: SPCB2 - Bank reconciliation checking
F53: CACB3 - Bank confirmation testing | G53: SPCB3 - Bank confirmation testing
B54: Payroll | C54: RSKPAY1 - Risk of misstatement of payroll expense due to recording of incorrect amount as payroll cost (i.e., due to updation of wrong salary cost in the payroll master file). | D54: O, C, A, CO | E54: Normal | F54: CAPAY2 - Biometric attendance report checking | G54: SPPAY1 - Recompute salary expense
G55: SPPAY3 - Check incentive computation
G56: SPPAY4 - Check salary payable balance
B57: Payroll | C57: RSKPAY2 - Risk of misstatement of payroll expense due to recording of payroll cost in the wrong period. | D57: A, CO | E57: Normal | F57: CAPAY2 - Biometric attendance report checking | G57: SPPAY1 - Recompute salary expense
G58: SPPAY3 - Check incentive computation
G59: SPPAY4 - Check salary payable balance
B60: Payroll | C60: RSKPAY3 - Risk of understatement of payroll cost because the withheld taxes and other deductions are not recorded (i.e., payroll cost is recorded for net payroll and not gross payroll). | D60: C, A | E60: Normal | F60: Nil | G60: SPPAY2 - Recalculate PF, ESI deductions
B61: Payroll | C61: RSKPAY4 - Risk of misstatement of Provident Fund and ESI expense recorded because the statutory rate of contribution applied is incorrect or contribution has not been calculated for all employees due to processing errors. | D61: C, A | E61: Normal | F61: Nil | G61: SPPAY2 - Recalculate PF, ESI deductions
B62: Payroll | C62: RSKPAY5 - Risk of misstatement of leave salary expense and accrual because the leave, salary and other relevant data provided for actuarial valuation is incorrect and disclosures required as per the financial reporting framework are not given | D62: C, A, CL | E62: Normal | F62: Nil | G62: SPPAY5 - Checking data given to actuary SPPAY6 - Ensuring compliance with disclosure reqmts
B63: Payroll | C63: RSKPAY6 - Risk that employee costs are not recorded in the correct ledgers according to their nature (direct wages, indirect costs, staff welfare etc) which could impact calculation of production overhead rates and consquently inventory valuation. | D63: CL, PD | E63: Normal | F63: Nil | G63: SPPAY7 - Employee cost segregation and POH calculation
B64: Inventory | C64: RSKINV1 - Risk of understatement of Inventory because inventory on hand and inventory received from suppliers are not included in inventory records. | D64: E,R, C, V | E64: Normal | F64: CAINV1 - Physical verification | G64: SPINV1 - Inventory test counts
G65: SPINV2 - Confirmation of stock with 3rd parties
B66: Inventory | C66: RSKINV2 - Risk of overstatement of Inventory because inventory records include inventory that has been sold to customers / consumed. | D66: E, R, C | E66: Normal | F66: CAINV1 - Physical verification | G66: SPINV1 - Inventory test counts
G67: SPINV2 - Confirmation of stock with 3rd parties
B68: Inventory | C68: RSKINV3 - Risk of overstatement of Inventory because inventory is old, obsolete, damaged, not usable or is saleable at amounts less than that at which it is recorded. | D68: V, A | E68: Normal | F68: CAINV2 - Segregation of damaged and good stock | G68: SPINV3 - Checking inventory valuation method
G69: SPINV4 - Using NRV for valuing damaged stock
B70: Inventory | C70: RSKINV4 - Risk of misstatement of Inventory because the prices used to value inventory and / or the valuation principles and methods used are incorrect and associated material costs and overheads (production and indirect overheads) are not allocated to Finished goods and work in progress on a reasonable basis | D70: V, A | E70: Normal | F70: Nil | G70: SPINV5 - Allocating overheads to stock
B71: Inventory | C71: RSKINV5 - Risk that inventory balances are intentionally misstated so as to ensure better working capital borrowing limits | D71: V, A, P&D | E71: Significant | F71: Nil | G71: SPDBT15 - Checking terms as per sanction letters SPINV6 - Verifying quarterly inventory statements submitted to banks
B72: Receivables | C72: RSKDRS1 - Risk of misstatement of Accounts receivable because invoices issued and recorded do not relate to valid sales / shipments or because invoices are not recorded at all. | D72: E, R | E72: Normal | F72: CARE1 - Comparison with orders and shipping documents | G72: SPRE1 - Validity of recorded sales transactions
G73: SPRE7 - Checking gate passes to ensure invoices are not fictitious
B74: Receivables | C74: RSKDRS2 - Risk of misstatement of Accounts receivable because of errors in the calculation of sales value on the invoice. | D74: R, V | E74: Normal | F74: CARE3 - Comparision with pricelists | G74: SPRE3 - Checking pricelists and discounts
F75: CARE4 - Checking invoice autocomputation
F76: CARE5 - Checking for unauthorised access
B77: Receivables | C77: RSKDRS3 - Risk of misstatement of Accounts receivable because receipts from customers is recorded more than once or are not recorded at all. | D77: E, R, V, C | E77: Significant | F77: CACB2 - Monthly bank reco testing | G77: SPCB2 - Bank reconciliation checking
F78: CACB3 - Bank confirmation testing | G78: SPCB3 - Bank confirmation testing | H78: Monthly customer ageing reports - Include under controls
G79: SPDRS1 - Drs ageing
A80: S | G80: SPDRS5 - Confirmation procedures as on BS date/subsequent testing.
G81: SPDRS6 - Confirmation procedures on other date/subsequent testing.
G82: SPDRS7 - Drs Turnover ratio checking
B83: Receivables | C83: RSKDRS4 - Risk of overstatement of Accounts receivable because of understatement of allowance for doubtful debts. | D83: R, V, A | E83: Normal | F83: Nil | G83: SPDRS1 - Drs ageing
G84: SPDRS2 - Check debtors provisioning
G85: SPDRS4 - Reconcile ageing report with GL
B86: Receivables | C86: RSKDRS5 - Risk of overstatement of bad debts because debtors are written off as bad without proper approvals | D86: E, R, V | E86: Normal | F86: CADRS3 - Approvals for writeoff of debts | G86: SPDRS3 - Approvals for writeoff of debts
B87: Receivables | C87: RSKDRS6 - Risk that debts due from directors, related parties of the entity are not separately disclosed as per reporting requirements | D87: P | E87: Normal | F87: Nil | G87: SPDRS8 - Cross check with related party workings to ensure that debtors are presented appropriately as per reporting requirements
B88: Investments | C88: RSKINMT1-Risk of misstatement of investment in chit funds since payments to chit companies are not correctly accounted in the books of account | D88: E, R, C, V | E88: Normal | F88: Nil | G88: SPINMT1 - Comparison of amounts booked with statements
G89: SPINMT2 - Comparison with confirmations
B90: Investments | C90: RSKINMT2-Risk of misstatement of investments in shares and mutual funds since amounts invested are not accounted and measured as per the requirements of relevant accounting standards | D90: E, R, V, A | E90: Normal | F90: Nil | G90: SPINMT3 - Comparison with statements and cost FMV comparison
B91: Investments | C91: RSKINMT3-Risk that investments made by the company are not appropriately classified and disclosed in the financial statements | D91: V, P&D | E91: Normal | F91: Nil | G91: SPINMT4 - Checking time period for liquidation for current/non current classification
G92: SPINMT5 - Comparison against corresponding liability if any and appropriate disclosure
B93: Equity | C93: RSKEQ1 - Risk of understatement of equity because shares issued during the year are not recorded in the general ledger. | D93: E, R, V | E93: Normal | F93: Nil | G93: SPEQ1 - Obtain schedule of changes in equity and confirm the balances
B94: Equity | C94: RSKEQ2 - Risk of understatement of equity because mandatory transfer to reserves on declaration / payment of dividend is not recorded. | D94: E, R, V | E94: Normal | F94: Nil | G94: SPEQ2 - Review minutes of TCWG
G95: SPEQ3 - Check statutory compliance of dividend payouts if any
B96: Equity | C96: RSKEQ3 - Risk of overstatement of equity because dividend declared on share capital plus corporate dividend tax are not recorded in the general ledger. | D96: V, A | E96: Normal | F96: Nil | G96: SPEQ2 - Review minutes of TCWG
G97: SPEQ3 - Check statutory compliance of dividend payouts if any
B98: Debt | C98: RSKDBT1 - Risk of overstatement of recorded debt (Eg: Due to non recording of payments, personal loans of directors/partners accounted in the firm's books etc) | D98: E, O, C | E98: Normal | F98: CADBT1 - Monitoring by lenders | G98: SPDBT1 - Check if all loan balances are accounted
F99: CACB2 - Monthly bank reco testing | G99: SPDBT2 - Checking with confirmations
B100: Debt | C100: RSKDBT3 - Risk of non compliance with the terms of the loan | D100: O | E100: Normal | F100: CADBT1 - Monitoring by lenders | G100: SPDBT5 - Check interest ledgers for penalties
G101: SPDBT15 - Checking terms as per sanction letters
B102: Debt | C102: RSKDBT4 - Risk of misstatement of loan balance and interest expense due to non recording/incorrect recording of interest expense | D102: O, C, V, A | E102: Normal | F102: Nil | G102: SPDBT6 - Check interest booked with statements
G103: SPDBT7 - Recalculate interest amount
...

Sheet Relating Assertions to Risks
J2: FAPs planned
B3: MCOTABD | C3: Assertion | D3: Assertion | F3: Risk | G3: Risk formatted | I3: Identified RoMM | J3: Controls | K3: Substantive
B4: Fixed Assets | C4: Allocation | D4: =LEFT(G4) -> A | E4: =IF(MID(G4,2,1)="R", "OK","CHECK") -> OK | F4: ARSKFA7 - Risk of misstatement of fixed assets because the depreciation method and / or depreciation rate adopted are not in compliance with the applicable statutes | G4: =TRIM(F4) -> ARSKFA7 - Risk of misstatement of fixed assets because the depreciation method and / or depreciation rate adopted are not in compliance with the applicable statutes | H4: =MID(G4,LEN(D4)+1,T4-LEN(D4)) -> RSKFA7 - Risk of misstatement of fixed assets because the depreciation method and / or depreciation rate adopted are not in compliance with the applicable statutes | I4: RSKFA7 - Risk of misstatement of fixed assets because the depreciation method and / or depreciation rate adopted are not in compliance with the applicable statutes | J4: NIL | K4: SPFA5 - Depreciation recomputation SPFA11 - Cross checking with Winman | T4: =LEN(G4) -> 164
B5: Fixed Assets | C5: Allocation | D5: =LEFT(G5) -> A | E5: =IF(MID(G5,2,1)="R", "OK","CHECK") -> OK | F5: ARSKFA3 - Risk of understatement of fixed assets because fixed assets purchased have been expensed and not capitalised. | G5: =TRIM(F5) -> ARSKFA3 - Risk of understatement of fixed assets because fixed assets purchased have been expensed and not capitalised. | H5: =MID(G5,LEN(D5)+1,T5-LEN(D5)) -> RSKFA3 - Risk of understatement of fixed assets because fixed assets purchased have been expensed and not capitalised. | I5: RSKFA3 - Risk of understatement of fixed assets because fixed assets purchased have been expensed and not capitalised. | J5: CAFA3 - Checking asset purchase requisitions CAFA4 - Asset PO verification CAFA5 - Asset invoice approval | K5: SPFA6 - Repairs & maint ledger scrutiny | T5: =LEN(G5) -> 119
B6: Fixed Assets | C6: Allocation | D6: =LEFT(G6) -> A | E6: =IF(MID(G6,2,1)="R", "OK","CHECK") -> OK | F6: ARSKFA4 - Risk of overstatement of fixed assets because repairs and maintenance expenses have been incorrectly capitalised as fixed assets. | G6: =TRIM(F6) -> ARSKFA4 - Risk of overstatement of fixed assets because repairs and maintenance expenses have been incorrectly capitalised as fixed assets. | H6: =MID(G6,LEN(D6)+1,T6-LEN(D6)) -> RSKFA4 - Risk of overstatement of fixed assets because repairs and maintenance expenses have been incorrectly capitalised as fixed assets. | I6: RSKFA4 - Risk of overstatement of fixed assets because repairs and maintenance expenses have been incorrectly capitalised as fixed assets. | J6: CAFA5 - Asset invoice approval CAFA9 - FA number tagging | K6: SPFA8 - GSTR2A verification for additions SPFA6 - Repairs & maint ledger scrutiny SPFA10 - Review of CWIP ledger & capitalisation | T6: =LEN(G6) -> 139
B7: Fixed Assets | C7: Allocation | D7: =LEFT(G7) -> A | E7: =IF(MID(G7,2,1)="R", "OK","CHECK") -> OK | F7: ARSKFA6 - Risk of misstatement of fixed assets because initial measurement, subsequent measurement and impairment testing of fixed assets have not been done in the manner specified in the financial reporting framework | G7: =TRIM(F7) -> ARSKFA6 - Risk of misstatement of fixed assets because initial measurement, subsequent measurement and impairment testing of fixed assets have not been done in the manner specified in the financial reporting framework | H7: =MID(G7,LEN(D7)+1,T7-LEN(D7)) -> RSKFA6 - Risk of misstatement of fixed assets because initial measurement, subsequent measurement and impairment testing of fixed assets have not been done in the manner specified in the financial reporting framework | I7: RSKFA6 - Risk of misstatement of fixed assets because initial measurement, subsequent measurement and impairment testing of fixed assets have not been done in the manner specified in the financial reporting framework | J7: CAFA5 - Asset invoice approval | K7: SPFA1 - Checking OB carried forward SPFA3 - Physical verification procedures SPFA9 - Checking GSTRs for asset sale SPFA7 - Impairment testing | T7: =LEN(G7) -> 217
B8: Fixed Assets | C8: Completeness | D8: =LEFT(G8) -> C | E8: =IF(MID(G8,2,1)="R", "OK","CHECK") -> OK | F8: CRSKFA1 - Risk of understatement of fixed assets because assets acquired by the entity are not recorded. | G8: =TRIM(F8) -> CRSKFA1 - Risk of understatement of fixed assets because assets acquired by the entity are not recorded. | H8: =MID(G8,LEN(D8)+1,T8-LEN(D8)) -> RSKFA1 - Risk of understatement of fixed assets because assets acquired by the entity are not recorded. | I8: RSKFA1 - Risk of understatement of fixed assets because assets acquired by the entity are not recorded. | J8: CACL5 - Payment approval CACB2 - Monthly bank reco testing | K8: SPFA8 - GSTR2A verification for additions SPFA2 - Additions vouching SPFA3 - Physical verification procedures SPCL2 - Creditors balance confirmation SPCB2 - Bank reconciliation checking | T8: =LEN(G8) -> 104
B9: Fixed Assets | C9: Completeness | D9: =LEFT(G9) -> C | E9: =IF(MID(G9,2,1)="R", "OK","CHECK") -> OK | F9: CRSKFA2 - Risk of understatement of fixed assets because assets in use and still owned by the entity have been wrongly recorded as disposed. | G9: =TRIM(F9) -> CRSKFA2 - Risk of understatement of fixed assets because assets in use and still owned by the entity have been wrongly recorded as disposed. | H9: =MID(G9,LEN(D9)+1,T9-LEN(D9)) -> RSKFA2 - Risk of understatement of fixed assets because assets in use and still owned by the entity have been wrongly recorded as disposed. | I9: RSKFA2 - Risk of understatement of fixed assets because assets in use and still owned by the entity have been wrongly recorded as disposed. | J9: NIL | K9: SPFA1 - Checking OB carried forward | T9: =LEN(G9) -> 140
B10: Fixed Assets | C10: Existence | D10: =LEFT(G10) -> E | E10: =IF(MID(G10,2,1)="R", "OK","CHECK") -> OK | F10: ERSKFA2 - Risk of understatement of fixed assets because assets in use and still owned by the entity have been wrongly recorded as disposed. | G10: =TRIM(F10) -> ERSKFA2 - Risk of understatement of fixed assets because assets in use and still owned by the entity have been wrongly recorded as disposed. | H10: =MID(G10,LEN(D10)+1,T10-LEN(D10)) -> RSKFA2 - Risk of understatement of fixed assets because assets in use and still owned by the entity have been wrongly recorded as disposed. | I10: RSKFA2 - Risk of understatement of fixed assets because assets in use and still owned by the entity have been wrongly recorded as disposed. | J10: NIL | K10: SPFA1 - Checking OB carried forward | T10: =LEN(G10) -> 140
B11: Fixed Assets | C11: Existence | D11: =LEFT(G11) -> E | E11: =IF(MID(G11,2,1)="R", "OK","CHECK") -> OK | F11: ERSKFA3 - Risk of understatement of fixed assets because fixed assets purchased have been expensed and not capitalised. | G11: =TRIM(F11) -> ERSKFA3 - Risk of understatement of fixed assets because fixed assets purchased have been expensed and not capitalised. | H11: =MID(G11,LEN(D11)+1,T11-LEN(D11)) -> RSKFA3 - Risk of understatement of fixed assets because fixed assets purchased have been expensed and not capitalised. | I11: RSKFA3 - Risk of understatement of fixed assets because fixed assets purchased have been expensed and not capitalised. | J11: CAFA3 - Checking asset purchase requisitions CAFA4 - Asset PO verification CAFA5 - Asset invoice approval | K11: SPFA6 - Repairs & maint ledger scrutiny | T11: =LEN(G11) -> 119
B12: Fixed Assets | C12: Existence | D12: =LEFT(G12) -> E | E12: =IF(MID(G12,2,1)="R", "OK","CHECK") -> OK | F12: ERSKFA4 - Risk of overstatement of fixed assets because repairs and maintenance expenses have been incorrectly capitalised as fixed assets. | G12: =TRIM(F12) -> ERSKFA4 - Risk of overstatement of fixed assets because repairs and maintenance expenses have been incorrectly capitalised as fixed assets. | H12: =MID(G12,LEN(D12)+1,T12-LEN(D12)) -> RSKFA4 - Risk of overstatement of fixed assets because repairs and maintenance expenses have been incorrectly capitalised as fixed assets. | I12: RSKFA4 - Risk of overstatement of fixed assets because repairs and maintenance expenses have been incorrectly capitalised as fixed assets. | J12: CAFA5 - Asset invoice approval CAFA9 - FA number tagging | K12: SPFA8 - GSTR2A verification for additions SPFA6 - Repairs & maint ledger scrutiny SPFA10 - Review of CWIP ledger & capitalisation | T12: =LEN(G12) -> 139
B13: Fixed Assets | C13: Existence | D13: =LEFT(G13) -> E | E13: =IF(MID(G13,2,1)="R", "OK","CHECK") -> OK | F13: ERSKFA5 - Risk of overstatement of fixed assets because assets disposed of have not been recorded in the fixed asset register / general ledger. | G13: =TRIM(F13) -> ERSKFA5 - Risk of overstatement of fixed assets because assets disposed of have not been recorded in the fixed asset register / general ledger. | H13: =MID(G13,LEN(D13)+1,T13-LEN(D13)) -> RSKFA5 - Risk of overstatement of fixed assets because assets disposed of have not been recorded in the fixed asset register / general ledger. | I13: RSKFA5 - Risk of overstatement of fixed assets because assets disposed of have not been recorded in the fixed asset register / general ledger. | J13: CAFA9 - FA number tagging | K13: SPFA1 - Checking OB carried forward SPFA3 - Physical verification procedures SPFA4 - Testing asset disposals SPFA9 - Checking GSTRs for asset sale | T13: =LEN(G13) -> 143
B14: Fixed Assets | C14: Existence | D14: =LEFT(G14) -> E | E14: =IF(MID(G14,2,1)="R", "OK","CHECK") -> OK | F14: ERSKFA6 - Risk of misstatement of fixed assets because initial measurement, subsequent measurement and impairment testing of fixed assets have not been done in the manner specified in the financial reporting framework | G14: =TRIM(F14) -> ERSKFA6 - Risk of misstatement of fixed assets because initial measurement, subsequent measurement and impairment testing of fixed assets have not been done in the manner specified in the financial reporting framework | H14: =MID(G14,LEN(D14)+1,T14-LEN(D14)) -> RSKFA6 - Risk of misstatement of fixed assets because initial measurement, subsequent measurement and impairment testing of fixed assets have not been done in the manner specified in the financial reporting framework | I14: RSKFA6 - Risk of misstatement of fixed assets because initial measurement, subsequent measurement and impairment testing of fixed assets have not been done in the manner specified in the financial reporting framework | J14: CAFA5 - Asset invoice approval | K14: SPFA1 - Checking OB carried forward SPFA3 - Physical verification procedures SPFA9 - Checking GSTRs for asset sale SPFA7 - Impairment testing | T14: =LEN(G14) -> 217
B15: Fixed Assets | C15: Presentation & Disclosure | D15: =LEFT(G15,3) -> P&D | E15: =IF(MID(G15,2,1)="R", "OK","CHECK") -> CHECK | F15: P&DRSKFA1 - Risk of understatement of fixed assets because assets acquired by the entity are not recorded. | G15: =TRIM(F15) -> P&DRSKFA1 - Risk of understatement of fixed assets because assets acquired by the entity are not recorded. | H15: =MID(G15,LEN(D15)+1,T15-LEN(D15)) -> RSKFA1 - Risk of understatement of fixed assets because assets acquired by the entity are not recorded. | I15: RSKFA1 - Risk of understatement of fixed assets because assets acquired by the entity are not recorded. | J15: CACL5 - Payment approval CACB2 - Monthly bank reco testing | K15: SPFA8 - GSTR2A verification for additions SPFA2 - Additions vouching SPFA3 - Physical verification procedures SPCL2 - Creditors balance confirmation SPCB2 - Bank reconciliation checking | T15: =LEN(G15) -> 106
B16: Fixed Assets | C16: Rights | D16: =LEFT(G16) -> R | E16: =IF(MID(G16,2,1)="R", "OK","CHECK") -> OK | F16: RRSKFA2 - Risk of understatement of fixed assets because assets in use and still owned by the entity have been wrongly recorded as disposed. | G16: =TRIM(F16) -> RRSKFA2 - Risk of understatement of fixed assets because assets in use and still owned by the entity have been wrongly recorded as disposed. | H16: =MID(G16,LEN(D16)+1,T16-LEN(D16)) -> RSKFA2 - Risk of understatement of fixed assets because assets in use and still owned by the entity have been wrongly recorded as disposed. | I16: RSKFA2 - Risk of understatement of fixed assets because assets in use and still owned by the entity have been wrongly recorded as disposed. | J16: NIL | K16: SPFA1 - Checking OB carried forward SPFA3 - Physical verification procedures SPFA9 - Checking GSTRs for asset sale | T16: =LEN(G16) -> 140
B17: Fixed Assets | C17: Rights | D17: =LEFT(G17) -> R | E17: =IF(MID(G17,2,1)="R", "OK","CHECK") -> OK | F17: RRSKFA3 - Risk of understatement of fixed assets because fixed assets purchased have been expensed and not capitalised. | G17: =TRIM(F17) -> RRSKFA3 - Risk of understatement of fixed assets because fixed assets purchased have been expensed and not capitalised. | H17: =MID(G17,LEN(D17)+1,T17-LEN(D17)) -> RSKFA3 - Risk of understatement of fixed assets because fixed assets purchased have been expensed and not capitalised. | I17: RSKFA3 - Risk of understatement of fixed assets because fixed assets purchased have been expensed and not capitalised. | J17: CAFA3 - Checking asset purchase requisitions CAFA4 - Asset PO verification CAFA5 - Asset invoice approval | K17: SPFA6 - Repairs & maint ledger scrutiny | T17: =LEN(G17) -> 119
B18: Fixed Assets | C18: Rights | D18: =LEFT(G18) -> R | E18: =IF(MID(G18,2,1)="R", "OK","CHECK") -> OK | F18: RRSKFA4 - Risk of overstatement of fixed assets because repairs and maintenance expenses have been incorrectly capitalised as fixed assets. | G18: =TRIM(F18) -> RRSKFA4 - Risk of overstatement of fixed assets because repairs and maintenance expenses have been incorrectly capitalised as fixed assets. | H18: =MID(G18,LEN(D18)+1,T18-LEN(D18)) -> RSKFA4 - Risk of overstatement of fixed assets because repairs and maintenance expenses have been incorrectly capitalised as fixed assets. | I18: RSKFA4 - Risk of overstatement of fixed assets because repairs and maintenance expenses have been incorrectly capitalised as fixed assets. | J18: CAFA5 - Asset invoice approval CAFA9 - FA number tagging | K18: SPFA8 - GSTR2A verification for additions SPFA6 - Repairs & maint ledger scrutiny SPFA10 - Review of CWIP ledger & capitalisation | T18: =LEN(G18) -> 139
B19: Fixed Assets | C19: Rights | D19: =LEFT(G19) -> R | E19: =IF(MID(G19,2,1)="R", "OK","CHECK") -> OK | F19: RRSKFA5 - Risk of overstatement of fixed assets because assets disposed of have not been recorded in the fixed asset register / general ledger. | G19: =TRIM(F19) -> RRSKFA5 - Risk of overstatement of fixed assets because assets disposed of have not been recorded in the fixed asset register / general ledger. | H19: =MID(G19,LEN(D19)+1,T19-LEN(D19)) -> RSKFA5 - Risk of overstatement of fixed assets because assets disposed of have not been recorded in the fixed asset register / general ledger. | I19: RSKFA5 - Risk of overstatement of fixed assets because assets disposed of have not been recorded in the fixed asset register / general ledger. | J19: CAFA9 - FA number tagging | K19: SPFA1 - Checking OB carried forward SPFA3 - Physical verification procedures SPFA4 - Testing asset disposals SPFA9 - Checking GSTRs for asset sale | T19: =LEN(G19) -> 143
B20: Fixed Assets | C20: Rights | D20: =LEFT(G20) -> R | E20: =IF(MID(G20,2,1)="R", "OK","CHECK") -> OK | F20: RRSKFA6 - Risk of misstatement of fixed assets because initial measurement, subsequent measurement and impairment testing of fixed assets have not been done in the manner specified in the financial reporting framework | G20: =TRIM(F20) -> RRSKFA6 - Risk of misstatement of fixed assets because initial measurement, subsequent measurement and impairment testing of fixed assets have not been done in the manner specified in the financial reporting framework | H20: =MID(G20,LEN(D20)+1,T20-LEN(D20)) -> RSKFA6 - Risk of misstatement of fixed assets because initial measurement, subsequent measurement and impairment testing of fixed assets have not been done in the manner specified in the financial reporting framework | I20: RSKFA6 - Risk of misstatement of fixed assets because initial measurement, subsequent measurement and impairment testing of fixed assets have not been done in the manner specified in the financial reporting framework | J20: CAFA5 - Asset invoice approval | K20: SPFA1 - Checking OB carried forward SPFA3 - Physical verification procedures SPFA9 - Checking GSTRs for asset sale SPFA7 - Impairment testing | T20: =LEN(G20) -> 217
B21: Fixed Assets | C21: Valuation | D21: =LEFT(G21) -> V | E21: =IF(MID(G21,2,1)="R", "OK","CHECK") -> OK | F21: VRSKFA7 - Risk of misstatement of fixed assets because the depreciation method and / or depreciation rate adopted are not in compliance with the applicable statutes | G21: =TRIM(F21) -> VRSKFA7 - Risk of misstatement of fixed assets because the depreciation method and / or depreciation rate adopted are not in compliance with the applicable statutes | H21: =MID(G21,LEN(D21)+1,T21-LEN(D21)) -> RSKFA7 - Risk of misstatement of fixed assets because the depreciation method and / or depreciation rate adopted are not in compliance with the applicable statutes | I21: RSKFA7 - Risk of misstatement of fixed assets because the depreciation method and / or depreciation rate adopted are not in compliance with the applicable statutes | J21: NIL | K21: SPFA5 - Depreciation recomputation SPFA11 - Cross checking with Winman | T21: =LEN(G21) -> 164
B22: Fixed Assets | C22: Valuation | D22: =LEFT(G22) -> V | E22: =IF(MID(G22,2,1)="R", "OK","CHECK") -> OK | F22: VRSKFA1 - Risk of understatement of fixed assets because assets acquired by the entity are not recorded. | G22: =TRIM(F22) -> VRSKFA1 - Risk of understatement of fixed assets because assets acquired by the entity are not recorded. | H22: =MID(G22,LEN(D22)+1,T22-LEN(D22)) -> RSKFA1 - Risk of understatement of fixed assets because assets acquired by the entity are not recorded. | I22: RSKFA1 - Risk of understatement of fixed assets because assets acquired by the entity are not recorded. | J22: CACL5 - Payment approval CACB2 - Monthly bank reco testing | K22: SPFA8 - GSTR2A verification for additions SPFA2 - Additions vouching SPFA3 - Physical verification procedures SPCL2 - Creditors balance confirmation SPCB2 - Bank reconciliation checking | T22: =LEN(G22) -> 104
B23: Fixed Assets | C23: Valuation | D23: =LEFT(G23) -> V | E23: =IF(MID(G23,2,1)="R", "OK","CHECK") -> OK | F23: VRSKFA3 - Risk of understatement of fixed assets because fixed assets purchased have been expensed and not capitalised. | G23: =TRIM(F23) -> VRSKFA3 - Risk of understatement of fixed assets because fixed assets purchased have been expensed and not capitalised. | H23: =MID(G23,LEN(D23)+1,T23-LEN(D23)) -> RSKFA3 - Risk of understatement of fixed assets because fixed assets purchased have been expensed and not capitalised. | I23: RSKFA3 - Risk of understatement of fixed assets because fixed assets purchased have been expensed and not capitalised. | J23: CAFA3 - Checking asset purchase requisitions CAFA4 - Asset PO verification CAFA5 - Asset invoice approval | K23: SPFA6 - Repairs & maint ledger scrutiny | T23: =LEN(G23) -> 119
B24: Fixed Assets | C24: Valuation | D24: =LEFT(G24) -> V | E24: =IF(MID(G24,2,1)="R", "OK","CHECK") -> OK | F24: VRSKFA4 - Risk of overstatement of fixed assets because repairs and maintenance expenses have been incorrectly capitalised as fixed assets. | G24: =TRIM(F24) -> VRSKFA4 - Risk of overstatement of fixed assets because repairs and maintenance expenses have been incorrectly capitalised as fixed assets. | H24: =MID(G24,LEN(D24)+1,T24-LEN(D24)) -> RSKFA4 - Risk of overstatement of fixed assets because repairs and maintenance expenses have been incorrectly capitalised as fixed assets. | I24: RSKFA4 - Risk of overstatement of fixed assets because repairs and maintenance expenses have been incorrectly capitalised as fixed assets. | J24: CAFA5 - Asset invoice approval CAFA9 - FA number tagging | K24: SPFA8 - GSTR2A verification for additions SPFA6 - Repairs & maint ledger scrutiny SPFA10 - Review of CWIP ledger & capitalisation | T24: =LEN(G24) -> 139
B25: Fixed Assets | C25: Valuation | D25: =LEFT(G25) -> V | E25: =IF(MID(G25,2,1)="R", "OK","CHECK") -> OK | F25: VRSKFA6 - Risk of misstatement of fixed assets because initial measurement, subsequent measurement and impairment testing of fixed assets have not been done in the manner specified in the financial reporting framework | G25: =TRIM(F25) -> VRSKFA6 - Risk of misstatement of fixed assets because initial measurement, subsequent measurement and impairment testing of fixed assets have not been done in the manner specified in the financial reporting framework | H25: =MID(G25,LEN(D25)+1,T25-LEN(D25)) -> RSKFA6 - Risk of misstatement of fixed assets because initial measurement, subsequent measurement and impairment testing of fixed assets have not been done in the manner specified in the financial reporting framework | I25: RSKFA6 - Risk of misstatement of fixed assets because initial measurement, subsequent measurement and impairment testing of fixed assets have not been done in the manner specified in the financial reporting framework | J25: CAFA5 - Asset invoice approval | K25: SPFA1 - Checking OB carried forward SPFA3 - Physical verification procedures SPFA9 - Checking GSTRs for asset sale SPFA7 - Impairment testing | T25: =LEN(G25) -> 217
B26: Fixed Assets | C26: Valuation | D26: =LEFT(G26) -> V | E26: =IF(MID(G26,2,1)="R", "OK","CHECK") -> OK | F26: VRSKFA2 - Risk of understatement of fixed assets because assets in use and still owned by the entity have been wrongly recorded as disposed. | G26: =TRIM(F26) -> VRSKFA2 - Risk of understatement of fixed assets because assets in use and still owned by the entity have been wrongly recorded as disposed. | H26: =MID(G26,LEN(D26)+1,T26-LEN(D26)) -> RSKFA2 - Risk of understatement of fixed assets because assets in use and still owned by the entity have been wrongly recorded as disposed. | I26: RSKFA2 - Risk of understatement of fixed assets because assets in use and still owned by the entity have been wrongly recorded as disposed. | J26: NIL | K26: SPFA1 - Checking OB carried forward SPFA3 - Physical verification procedures SPFA9 - Checking GSTRs for asset sale | T26: =LEN(G26) -> 140
B27: Cash & Bank | C27: Completeness | D27: =LEFT(G27) -> C | E27: =IF(MID(G27,2,1)="R", "OK","CHECK") -> OK | F27: CRSKCB6 - Risk of understatement of Bank because interest accrued in the bank accounts have not been recorded by the entity. | G27: =TRIM(F27) -> CRSKCB6 - Risk of understatement of Bank because interest accrued in the bank accounts have not been recorded by the entity. | H27: =MID(G27,LEN(D27)+1,T27-LEN(D27)) -> RSKCB6 - Risk of understatement of Bank because interest accrued in the bank accounts have not been recorded by the entity. | I27: RSKCB6 - Risk of understatement of Bank because interest accrued in the bank accounts have not been recorded by the entity. | J27: CACB2 - Monthly bank reco testing CACB3 - Bank confirmation testing | K27: SPCB2 - Bank reconciliation checking SPCB3 - Bank confirmation testing | T27: =LEN(G27) -> 124
... B54: Payroll | C54: Completeness | D54: =LEFT(G54) -> C | E54: =IF(MID(G54,2,1)="R", "OK","CHECK") -> OK | F54: CRSKPAY1 - Risk of misstatement of payroll expense due to recording of incorrect amount as payroll cost (i.e., due to updation of wrong salary cost in the payroll master file). | G54: =TRIM(F54) -> CRSKPAY1 - Risk of misstatement of payroll expense due to recording of incorrect amount as payroll cost (i.e., due to updation of wrong salary cost in the payroll master file). | H54: =MID(G54,LEN(D54)+1,T54-LEN(D54)) -> RSKPAY1 - Risk of misstatement of payroll expense due to recording of incorrect amount as payroll cost (i.e., due to updation of wrong salary cost in the payroll master file). | I54: RSKPAY1 - Risk of misstatement of payroll expense due to recording of incorrect amount as payroll cost (i.e., due to updation of wrong salary cost in the payroll master file). | J54: CAPAY2 - Biometric attendance report checking | K54: SPPAY1 - Recompute salary expense SPPAY3 - Check incentive computation SPPAY4 - Check salary payable balance | T54: =LEN(G54) -> 176
B55: Payroll | C55: Classification | D55: =LEFT(G55,2) -> CL | E55: =IF(MID(G55,2,1)="R", "OK","CHECK") -> CHECK | F55: CLRSKPAY6 - Risk that employee costs are not recorded in the correct ledgers according to their nature (direct wages, indirect costs, staff welfare etc) which could impact calculation of production overhead rates and consquently inventory valuation. | G55: =TRIM(F55) -> CLRSKPAY6 - Risk that employee costs are not recorded in the correct ledgers according to their nature (direct wages, indirect costs, staff welfare etc) which could impact calculation of production overhead rates and consquently inventory valuation. | H55: =MID(G55,LEN(D55)+1,T55-LEN(D55)) -> RSKPAY6 - Risk that employee costs are not recorded in the correct ledgers according to their nature (direct wages, indirect costs, staff welfare etc) which could impact calculation of production overhead rates and consquently inventory valuation. | I55: RSKPAY6 - Risk that employee costs are not recorded in the correct ledgers according to their nature (direct wages, indirect costs, staff welfare etc) which could impact calculation of production overhead rates and consquently inventory valuation. | J55: NIL | K55: SPPAY7 - Employee cost segregation and POH calculation | T55: =LEN(G55) -> 249
B56: Payroll | C56: Classification | D56: =LEFT(G56,2) -> CL | E56: =IF(MID(G56,2,1)="R", "OK","CHECK") -> CHECK | F56: CLRSKPAY5 - Risk of misstatement of leave salary expense and accrual because the leave, salary and other relevant data provided for actuarial valuation is incorrect and disclosures required as per the financial reporting framework are not given | G56: =TRIM(F56) -> CLRSKPAY5 - Risk of misstatement of leave salary expense and accrual because the leave, salary and other relevant data provided for actuarial valuation is incorrect and disclosures required as per the financial reporting framework are not given | H56: =MID(G56,LEN(D56)+1,T56-LEN(D56)) -> RSKPAY5 - Risk of misstatement of leave salary expense and accrual because the leave, salary and other relevant data provided for actuarial valuation is incorrect and disclosures required as per the financial reporting framework are not given | I56: RSKPAY5 - Risk of misstatement of leave salary expense and accrual because the leave, salary and other relevant data provided for actuarial valuation is incorrect and disclosures required as per the financial reporting framework are not given | J56: NIL | K56: SPPAY5 - Checking data given to actuary SPPAY6 - Ensuring compliance with disclosure reqmts | T56: =LEN(G56) -> 244
B57: Payroll | C57: Cutoff | D57: =LEFT(G57,2) -> CO | E57: =IF(MID(G57,2,1)="R", "OK","CHECK") -> CHECK | F57: CORSKPAY2 - Risk of misstatement of payroll expense due to recording of payroll cost in the wrong period. | G57: =TRIM(F57) -> CORSKPAY2 - Risk of misstatement of payroll expense due to recording of payroll cost in the wrong period. | H57: =MID(G57,LEN(D57)+1,T57-LEN(D57)) -> RSKPAY2 - Risk of misstatement of payroll expense due to recording of payroll cost in the wrong period. | I57: RSKPAY2 - Risk of misstatement of payroll expense due to recording of payroll cost in the wrong period. | J57: CAPAY2 - Biometric attendance report checking | K57: SPPAY1 - Recompute salary expense SPPAY3 - Check incentive computation SPPAY4 - Check salary payable balance | T57: =LEN(G57) -> 105
B58: Payroll | C58: Cutoff | D58: =LEFT(G58,2) -> CO | E58: =IF(MID(G58,2,1)="R", "OK","CHECK") -> CHECK | F58: CORSKPAY1 - Risk of misstatement of payroll expense due to recording of incorrect amount as payroll cost (i.e., due to updation of wrong salary cost in the payroll master file). | G58: =TRIM(F58) -> CORSKPAY1 - Risk of misstatement of payroll expense due to recording of incorrect amount as payroll cost (i.e., due to updation of wrong salary cost in the payroll master file). | H58: =MID(G58,LEN(D58)+1,T58-LEN(D58)) -> RSKPAY1 - Risk of misstatement of payroll expense due to recording of incorrect amount as payroll cost (i.e., due to updation of wrong salary cost in the payroll master file). | I58: RSKPAY1 - Risk of misstatement of payroll expense due to recording of incorrect amount as payroll cost (i.e., due to updation of wrong salary cost in the payroll master file). | J58: CAPAY2 - Biometric attendance report checking | K58: SPPAY1 - Recompute salary expense SPPAY3 - Check incentive computation SPPAY4 - Check salary payable balance | T58: =LEN(G58) -> 177
B59: Payroll | C59: Occurrence | D59: =LEFT(G59) -> O | E59: =IF(MID(G59,2,1)="R", "OK","CHECK") -> OK | F59: ORSKPAY1 - Risk of misstatement of payroll expense due to recording of incorrect amount as payroll cost (i.e., due to updation of wrong salary cost in the payroll master file). | G59: =TRIM(F59) -> ORSKPAY1 - Risk of misstatement of payroll expense due to recording of incorrect amount as payroll cost (i.e., due to updation of wrong salary cost in the payroll master file). | H59: =MID(G59,LEN(D59)+1,T59-LEN(D59)) -> RSKPAY1 - Risk of misstatement of payroll expense due to recording of incorrect amount as payroll cost (i.e., due to updation of wrong salary cost in the payroll master file). | I59: RSKPAY1 - Risk of misstatement of payroll expense due to recording of incorrect amount as payroll cost (i.e., due to updation of wrong salary cost in the payroll master file). | J59: CAPAY2 - Biometric attendance report checking | K59: SPPAY1 - Recompute salary expense SPPAY3 - Check incentive computation SPPAY4 - Check salary payable balance | T59: =LEN(G59) -> 176
B60: Payroll | C60: Presentation & Disclosure | D60: =LEFT(G60,3) -> P&D | E60: =IF(MID(G60,2,1)="R", "OK","CHECK") -> CHECK | F60: P&DRSKPAY6 - Risk that employee costs are not recorded in the correct ledgers according to their nature (direct wages, indirect costs, staff welfare etc) which could impact calculation of production overhead rates and consquently inventory valuation. | G60: =TRIM(F60) -> P&DRSKPAY6 - Risk that employee costs are not recorded in the correct ledgers according to their nature (direct wages, indirect costs, staff welfare etc) which could impact calculation of production overhead rates and consquently inventory valuation. | H60: =MID(G60,LEN(D60)+1,T60-LEN(D60)) -> RSKPAY6 - Risk that employee costs are not recorded in the correct ledgers according to their nature (direct wages, indirect costs, staff welfare etc) which could impact calculation of production overhead rates and consquently inventory valuation. | I60: RSKPAY6 - Risk that employee costs are not recorded in the correct ledgers according to their nature (direct wages, indirect costs, staff welfare etc) which could impact calculation of production overhead rates and consquently inventory valuation. | J60: NIL | K60: SPPAY7 - Employee cost segregation and POH calculation | T60: =LEN(G60) -> 250
B61: Inventory | C61: Allocation | D61: =LEFT(G61) -> A | E61: =IF(MID(G61,2,1)="R", "OK","CHECK") -> OK | F61: ARSKINV3 - Risk of overstatement of Inventory because inventory is old, obsolete, damaged, not usable or is saleable at amounts less than that at which it is recorded. | G61: =TRIM(F61) -> ARSKINV3 - Risk of overstatement of Inventory because inventory is old, obsolete, damaged, not usable or is saleable at amounts less than that at which it is recorded. | H61: =MID(G61,LEN(D61)+1,T61-LEN(D61)) -> RSKINV3 - Risk of overstatement of Inventory because inventory is old, obsolete, damaged, not usable or is saleable at amounts less than that at which it is recorded. | I61: RSKINV3 - Risk of overstatement of Inventory because inventory is old, obsolete, damaged, not usable or is saleable at amounts less than that at which it is recorded. | J61: CAINV2 - Segregation of damaged and good stock | K61: SPINV3 - Checking inventory valuation method SPINV4 - Using NRV for valuing damaged stock | T61: =LEN(G61) -> 167
B62: Inventory | C62: Allocation | D62: =LEFT(G62) -> A | E62: =IF(MID(G62,2,1)="R", "OK","CHECK") -> OK | F62: ARSKINV4 - Risk of misstatement of Inventory because the prices used to value inventory and / or the valuation principles and methods used are incorrect and associated material costs and overheads (production and indirect overheads) are not allocated to Finished goods and work in progress on a reasonable basis | G62: =TRIM(F62) -> ARSKINV4 - Risk of misstatement of Inventory because the prices used to value inventory and / or the valuation principles and methods used are incorrect and associated material costs and overheads (production and indirect overheads) are not allocated to Finished goods and work in progress on a reasonable basis | H62: =MID(G62,LEN(D62)+1,T62-LEN(D62)) -> RSKINV4 - Risk of misstatement of Inventory because the prices used to value inventory and / or the valuation principles and methods used are incorrect and associated material costs and overheads (production and indirect overheads) are not allocated to Finished goods and work in progress on a reasonable basis | I62: RSKINV4 - Risk of misstatement of Inventory because the prices used to value inventory and / or the valuation principles and methods used are incorrect and associated material costs and overheads (production and indirect overheads) are not allocated to Finished goods and work in progress on a reasonable basis | J62: NIL | K62: SPINV5 - Allocating overheads to stock | T62: =LEN(G62) -> 311
B63: Inventory | C63: Allocation | D63: =LEFT(G63) -> A | E63: =IF(MID(G63,2,1)="R", "OK","CHECK") -> OK | F63: ARSKINV5 - Risk that inventory balances are intentionally misstated so as to ensure better working capital borrowing limits | G63: =TRIM(F63) -> ARSKINV5 - Risk that inventory balances are intentionally misstated so as to ensure better working capital borrowing limits | H63: =MID(G63,LEN(D63)+1,T63-LEN(D63)) -> RSKINV5 - Risk that inventory balances are intentionally misstated so as to ensure better working capital borrowing limits | I63: RSKINV5 - Risk that inventory balances are intentionally misstated so as to ensure better working capital borrowing limits | J63: NIL | K63: SPDBT15 - Checking terms as per sanction letters SPINV6 - Verifying quarterly inventory statements submitted to banks | T63: =LEN(G63) -> 123
B64: Inventory | C64: Completeness | D64: =LEFT(G64) -> C | E64: =IF(MID(G64,2,1)="R", "OK","CHECK") -> OK | F64: CRSKINV1 - Risk of understatement of Inventory because inventory on hand and inventory received from suppliers are not included in inventory records. | G64: =TRIM(F64) -> CRSKINV1 - Risk of understatement of Inventory because inventory on hand and inventory received from suppliers are not included in inventory records. | H64: =MID(G64,LEN(D64)+1,T64-LEN(D64)) -> RSKINV1 - Risk of understatement of Inventory because inventory on hand and inventory received from suppliers are not included in inventory records. | I64: RSKINV1 - Risk of understatement of Inventory because inventory on hand and inventory received from suppliers are not included in inventory records. | J64: CAINV1 - Physical verification | K64: SPINV1 - Inventory test counts SPINV2 - Confirmation of stock with 3rd parties | T64: =LEN(G64) -> 149
B65: Inventory | C65: Completeness | D65: =LEFT(G65) -> C | E65: =IF(MID(G65,2,1)="R", "OK","CHECK") -> OK | F65: CRSKINV2 - Risk of overstatement of Inventory because inventory records include inventory that has been sold to customers / consumed. | G65: =TRIM(F65) -> CRSKINV2 - Risk of overstatement of Inventory because inventory records include inventory that has been sold to customers / consumed. | H65: =MID(G65,LEN(D65)+1,T65-LEN(D65)) -> RSKINV2 - Risk of overstatement of Inventory because inventory records include inventory that has been sold to customers / consumed. | I65: RSKINV2 - Risk of overstatement of Inventory because inventory records include inventory that has been sold to customers / consumed. | J65: CAINV1 - Physical verification | K65: SPINV1 - Inventory test counts SPINV2 - Confirmation of stock with 3rd parties | T65: =LEN(G65) -> 133
B66: Inventory | C66: Existence | D66: =LEFT(G66) -> E | E66: =IF(MID(G66,2,1)="R", "OK","CHECK") -> OK | F66: ERSKINV1 - Risk of understatement of Inventory because inventory on hand and inventory received from suppliers are not included in inventory records. | G66: =TRIM(F66) -> ERSKINV1 - Risk of understatement of Inventory because inventory on hand and inventory received from suppliers are not included in inventory records. | H66: =MID(G66,LEN(D66)+1,T66-LEN(D66)) -> RSKINV1 - Risk of understatement of Inventory because inventory on hand and inventory received from suppliers are not included in inventory records. | I66: RSKINV1 - Risk of understatement of Inventory because inventory on hand and inventory received from suppliers are not included in inventory records. | J66: CAINV1 - Physical verification | K66: SPINV1 - Inventory test counts SPINV2 - Confirmation of stock with 3rd parties | T66: =LEN(G66) -> 149
B67: Inventory | C67: Existence | D67: =LEFT(G67) -> E | E67: =IF(MID(G67,2,1)="R", "OK","CHECK") -> OK | F67: ERSKINV2 - Risk of overstatement of Inventory because inventory records include inventory that has been sold to customers / consumed. | G67: =TRIM(F67) -> ERSKINV2 - Risk of overstatement of Inventory because inventory records include inventory that has been sold to customers / consumed. | H67: =MID(G67,LEN(D67)+1,T67-LEN(D67)) -> RSKINV2 - Risk of overstatement of Inventory because inventory records include inventory that has been sold to customers / consumed. | I67: RSKINV2 - Risk of overstatement of Inventory because inventory records include inventory that has been sold to customers / consumed. | J67: CAINV1 - Physical verification | K67: SPINV1 - Inventory test counts SPINV2 - Confirmation of stock with 3rd parties | T67: =LEN(G67) -> 133
B68: Inventory | C68: Presentation & Disclosure | D68: =LEFT(G68,3) -> P&D | E68: =IF(MID(G68,2,1)="R", "OK","CHECK") -> CHECK | F68: P&DRSKINV5 - Risk that inventory balances are intentionally misstated so as to ensure better working capital borrowing limits | G68: =TRIM(F68) -> P&DRSKINV5 - Risk that inventory balances are intentionally misstated so as to ensure better working capital borrowing limits | H68: =MID(G68,LEN(D68)+1,T68-LEN(D68)) -> RSKINV5 - Risk that inventory balances are intentionally misstated so as to ensure better working capital borrowing limits | I68: RSKINV5 - Risk that inventory balances are intentionally misstated so as to ensure better working capital borrowing limits | J68: NIL | K68: SPDBT15 - Checking terms as per sanction letters SPINV6 - Verifying quarterly inventory statements submitted to banks | T68: =LEN(G68) -> 125
B69: Inventory | C69: Rights | D69: =LEFT(G69) -> R | E69: =IF(MID(G69,2,1)="R", "OK","CHECK") -> OK | F69: RRSKINV1 - Risk of understatement of Inventory because inventory on hand and inventory received from suppliers are not included in inventory records. | G69: =TRIM(F69) -> RRSKINV1 - Risk of understatement of Inventory because inventory on hand and inventory received from suppliers are not included in inventory records. | H69: =MID(G69,LEN(D69)+1,T69-LEN(D69)) -> RSKINV1 - Risk of understatement of Inventory because inventory on hand and inventory received from suppliers are not included in inventory records. | I69: RSKINV1 - Risk of understatement of Inventory because inventory on hand and inventory received from suppliers are not included in inventory records. | J69: CAINV1 - Physical verification | K69: SPINV1 - Inventory test counts SPINV2 - Confirmation of stock with 3rd parties | T69: =LEN(G69) -> 149
B70: Inventory | C70: Rights | D70: =LEFT(G70) -> R | E70: =IF(MID(G70,2,1)="R", "OK","CHECK") -> OK | F70: RRSKINV2 - Risk of overstatement of Inventory because inventory records include inventory that has been sold to customers / consumed. | G70: =TRIM(F70) -> RRSKINV2 - Risk of overstatement of Inventory because inventory records include inventory that has been sold to customers / consumed. | H70: =MID(G70,LEN(D70)+1,T70-LEN(D70)) -> RSKINV2 - Risk of overstatement of Inventory because inventory records include inventory that has been sold to customers / consumed. | I70: RSKINV2 - Risk of overstatement of Inventory because inventory records include inventory that has been sold to customers / consumed. | J70: CAINV1 - Physical verification | K70: SPINV1 - Inventory test counts SPINV2 - Confirmation of stock with 3rd parties | T70: =LEN(G70) -> 133
B71: Inventory | C71: Valuation | D71: =LEFT(G71) -> V | E71: =IF(MID(G71,2,1)="R", "OK","CHECK") -> OK | F71: VRSKINV3 - Risk of overstatement of Inventory because inventory is old, obsolete, damaged, not usable or is saleable at amounts less than that at which it is recorded. | G71: =TRIM(F71) -> VRSKINV3 - Risk of overstatement of Inventory because inventory is old, obsolete, damaged, not usable or is saleable at amounts less than that at which it is recorded. | H71: =MID(G71,LEN(D71)+1,T71-LEN(D71)) -> RSKINV3 - Risk of overstatement of Inventory because inventory is old, obsolete, damaged, not usable or is saleable at amounts less than that at which it is recorded. | I71: RSKINV3 - Risk of overstatement of Inventory because inventory is old, obsolete, damaged, not usable or is saleable at amounts less than that at which it is recorded. | J71: CAINV2 - Segregation of damaged and good stock | K71: SPINV3 - Checking inventory valuation method SPINV4 - Using NRV for valuing damaged stock | T71: =LEN(G71) -> 167
B72: Inventory | C72: Valuation | D72: =LEFT(G72) -> V | E72: =IF(MID(G72,2,1)="R", "OK","CHECK") -> OK | F72: VRSKINV4 - Risk of misstatement of Inventory because the prices used to value inventory and / or the valuation principles and methods used are incorrect and associated material costs and overheads (production and indirect overheads) are not allocated to Finished goods and work in progress on a reasonable basis | G72: =TRIM(F72) -> VRSKINV4 - Risk of misstatement of Inventory because the prices used to value inventory and / or the valuation principles and methods used are incorrect and associated material costs and overheads (production and indirect overheads) are not allocated to Finished goods and work in progress on a reasonable basis | H72: =MID(G72,LEN(D72)+1,T72-LEN(D72)) -> RSKINV4 - Risk of misstatement of Inventory because the prices used to value inventory and / or the valuation principles and methods used are incorrect and associated material costs and overheads (production and indirect overheads) are not allocated to Finished goods and work in progress on a reasonable basis | I72: RSKINV4 - Risk of misstatement of Inventory because the prices used to value inventory and / or the valuation principles and methods used are incorrect and associated material costs and overheads (production and indirect overheads) are not allocated to Finished goods and work in progress on a reasonable basis | J72: NIL | K72: SPINV5 - Allocating overheads to stock | T72: =LEN(G72) -> 311
B73: Inventory | C73: Valuation | D73: =LEFT(G73) -> V | E73: =IF(MID(G73,2,1)="R", "OK","CHECK") -> OK | F73: VRSKINV5 - Risk that inventory balances are intentionally misstated so as to ensure better working capital borrowing limits | G73: =TRIM(F73) -> VRSKINV5 - Risk that inventory balances are intentionally misstated so as to ensure better working capital borrowing limits | H73: =MID(G73,LEN(D73)+1,T73-LEN(D73)) -> RSKINV5 - Risk that inventory balances are intentionally misstated so as to ensure better working capital borrowing limits | I73: RSKINV5 - Risk that inventory balances are intentionally misstated so as to ensure better working capital borrowing limits | J73: NIL | K73: SPDBT15 - Checking terms as per sanction letters SPINV6 - Verifying quarterly inventory statements submitted to banks | T73: =LEN(G73) -> 123
B74: Inventory | C74: Valuation | D74: =LEFT(G74) -> V | E74: =IF(MID(G74,2,1)="R", "OK","CHECK") -> OK | F74: VRSKINV1 - Risk of understatement of Inventory because inventory on hand and inventory received from suppliers are not included in inventory records. | G74: =TRIM(F74) -> VRSKINV1 - Risk of understatement of Inventory because inventory on hand and inventory received from suppliers are not included in inventory records. | H74: =MID(G74,LEN(D74)+1,T74-LEN(D74)) -> RSKINV1 - Risk of understatement of Inventory because inventory on hand and inventory received from suppliers are not included in inventory records. | I74: RSKINV1 - Risk of understatement of Inventory because inventory on hand and inventory received from suppliers are not included in inventory records. | J74: CAINV1 - Physical verification | K74: SPINV1 - Inventory test counts SPINV2 - Confirmation of stock with 3rd parties | T74: =LEN(G74) -> 149
B75: Receivables | C75: Allocation | D75: =LEFT(G75) -> A | E75: =IF(MID(G75,2,1)="R", "OK","CHECK") -> OK | F75: ARSKDRS4 - Risk of overstatement of Accounts receivable because of understatement of allowance for doubtful debts. | G75: =TRIM(F75) -> ARSKDRS4 - Risk of overstatement of Accounts receivable because of understatement of allowance for doubtful debts. | H75: =MID(G75,LEN(D75)+1,T75-LEN(D75)) -> RSKDRS4 - Risk of overstatement of Accounts receivable because of understatement of allowance for doubtful debts. | I75: RSKDRS4 - Risk of overstatement of Accounts receivable because of understatement of allowance for doubtful debts. | J75: NIL | K75: SPDRS1 - Drs ageing SPDRS2 - Check debtors provisioning SPDRS4 - Reconcile ageing report with GL | T75: =LEN(G75) -> 114
B76: Receivables | C76: Completeness | D76: =LEFT(G76) -> C | E76: =IF(MID(G76,2,1)="R", "OK","CHECK") -> OK | F76: CRSKDRS3 - Risk of misstatement of Accounts receivable because receipts from customers is recorded more than once or are not recorded at all. | G76: =TRIM(F76) -> CRSKDRS3 - Risk of misstatement of Accounts receivable because receipts from customers is recorded more than once or are not recorded at all. | H76: =MID(G76,LEN(D76)+1,T76-LEN(D76)) -> RSKDRS3 - Risk of misstatement of Accounts receivable because receipts from customers is recorded more than once or are not recorded at all. | I76: RSKDRS3 - Risk of misstatement of Accounts receivable because receipts from customers is recorded more than once or are not recorded at all. | J76: CACB2 - Monthly bank reco testing CACB3 - Bank confirmation testing | K76: SPCB2 - Bank reconciliation checking SPCB3 - Bank confirmation testing SPDRS1 - Drs ageing SPDRS5 - Confirmation procedures as on BS date/subsequent testing. SPDRS6 - Confirmation procedures on other date/subsequent testing. SPDRS7 - Drs Turnover ratio checking | T76: =LEN(G76) -> 141
B77: Receivables | C77: Existence | D77: =LEFT(G77) -> E | E77: =IF(MID(G77,2,1)="R", "OK","CHECK") -> OK | F77: ERSKDRS1 - Risk of misstatement of Accounts receivable because invoices issued and recorded do not relate to valid sales / shipments or because invoices are not recorded at all. | G77: =TRIM(F77) -> ERSKDRS1 - Risk of misstatement of Accounts receivable because invoices issued and recorded do not relate to valid sales / shipments or because invoices are not recorded at all. | H77: =MID(G77,LEN(D77)+1,T77-LEN(D77)) -> RSKDRS1 - Risk of misstatement of Accounts receivable because invoices issued and recorded do not relate to valid sales / shipments or because invoices are not recorded at all. | I77: RSKDRS1 - Risk of misstatement of Accounts receivable because invoices issued and recorded do not relate to valid sales / shipments or because invoices are not recorded at all. | J77: CACB2 - Monthly bank reco testing | K77: CACB3 - Bank confirmation testing | T77: =LEN(G77) -> 177
B78: Receivables | C78: Existence | D78: =LEFT(G78) -> E | E78: =IF(MID(G78,2,1)="R", "OK","CHECK") -> OK | F78: ERSKDRS3 - Risk of misstatement of Accounts receivable because receipts from customers is recorded more than once or are not recorded at all. | G78: =TRIM(F78) -> ERSKDRS3 - Risk of misstatement of Accounts receivable because receipts from customers is recorded more than once or are not recorded at all. | H78: =MID(G78,LEN(D78)+1,T78-LEN(D78)) -> RSKDRS3 - Risk of misstatement of Accounts receivable because receipts from customers is recorded more than once or are not recorded at all. | I78: RSKDRS3 - Risk of misstatement of Accounts receivable because receipts from customers is recorded more than once or are not recorded at all. | J78: CACB2 - Monthly bank reco testing CACB3 - Bank confirmation testing | K78: SPCB2 - Bank reconciliation checking SPCB3 - Bank confirmation testing SPDRS1 - Drs ageing SPDRS5 - Confirmation procedures as on BS date/subsequent testing. SPDRS6 - Confirmation procedures on other date/subsequent testing. SPDRS7 - Drs Turnover ratio checking | T78: =LEN(G78) -> 141
B79: Receivables | C79: Existence | D79: =LEFT(G79) -> E | E79: =IF(MID(G79,2,1)="R", "OK","CHECK") -> OK | F79: ERSKDRS5 - Risk of overstatement of bad debts because debtors are written off as bad without proper approvals | G79: =TRIM(F79) -> ERSKDRS5 - Risk of overstatement of bad debts because debtors are written off as bad without proper approvals | H79: =MID(G79,LEN(D79)+1,T79-LEN(D79)) -> RSKDRS5 - Risk of overstatement of bad debts because debtors are written off as bad without proper approvals | I79: RSKDRS5 - Risk of overstatement of bad debts because debtors are written off as bad without proper approvals | J79: CADRS3 - Approvals for writeoff of debts | K79: SPDRS3 - Approvals for writeoff of debts | T79: =LEN(G79) -> 109
B80: Receivables | C80: Presentation & Disclosure | D80: =LEFT(G80,3) -> P&D | E80: =IF(MID(G80,2,1)="R", "OK","CHECK") -> CHECK | F80: P&DRSKDRS6 - Risk that debts due from directors, related parties of the entity are not separately disclosed as per reporting requirements | G80: =TRIM(F80) -> P&DRSKDRS6 - Risk that debts due from directors, related parties of the entity are not separately disclosed as per reporting requirements | H80: =MID(G80,LEN(D80)+1,T80-LEN(D80)) -> RSKDRS6 - Risk that debts due from directors, related parties of the entity are not separately disclosed as per reporting requirements | I80: RSKDRS6 - Risk that debts due from directors, related parties of the entity are not separately disclosed as per reporting requirements | J80: NIL | K80: SPDRS8 - Cross check with related party workings to ensure that debtors are presented appropriately as per reporting requirements | T80: =LEN(G80) -> 137
B81: Receivables | C81: Rights | D81: =LEFT(G81) -> R | E81: =IF(MID(G81,2,1)="R", "OK","CHECK") -> OK | F81: RRSKDRS2 - Risk of misstatement of Accounts receivable because of errors in the calculation of sales value on the invoice. | G81: =TRIM(F81) -> RRSKDRS2 - Risk of misstatement of Accounts receivable because of errors in the calculation of sales value on the invoice. | H81: =MID(G81,LEN(D81)+1,T81-LEN(D81)) -> RSKDRS2 - Risk of misstatement of Accounts receivable because of errors in the calculation of sales value on the invoice. | I81: RSKDRS2 - Risk of misstatement of Accounts receivable because of errors in the calculation of sales value on the invoice. | J81: CARE3 - Comparision with pricelists CARE4 - Checking invoice autocomputation CARE5 - Checking for unauthorised access | K81: SPRE3 - Checking pricelists and discounts | T81: =LEN(G81) -> 122
B82: Receivables | C82: Rights | D82: =LEFT(G82) -> R | E82: =IF(MID(G82,2,1)="R", "OK","CHECK") -> OK | F82: RRSKDRS4 - Risk of overstatement of Accounts receivable because of understatement of allowance for doubtful debts. | G82: =TRIM(F82) -> RRSKDRS4 - Risk of overstatement of Accounts receivable because of understatement of allowance for doubtful debts. | H82: =MID(G82,LEN(D82)+1,T82-LEN(D82)) -> RSKDRS4 - Risk of overstatement of Accounts receivable because of understatement of allowance for doubtful debts. | I82: RSKDRS4 - Risk of overstatement of Accounts receivable because of understatement of allowance for doubtful debts. | J82: NIL | K82: SPDRS1 - Drs ageing SPDRS2 - Check debtors provisioning SPDRS4 - Reconcile ageing report with GL | T82: =LEN(G82) -> 114
B83: Receivables | C83: Rights | D83: =LEFT(G83) -> R | E83: =IF(MID(G83,2,1)="R", "OK","CHECK") -> OK | F83: RRSKDRS1 - Risk of misstatement of Accounts receivable because invoices issued and recorded do not relate to valid sales / shipments or because invoices are not recorded at all. | G83: =TRIM(F83) -> RRSKDRS1 - Risk of misstatement of Accounts receivable because invoices issued and recorded do not relate to valid sales / shipments or because invoices are not recorded at all. | H83: =MID(G83,LEN(D83)+1,T83-LEN(D83)) -> RSKDRS1 - Risk of misstatement of Accounts receivable because invoices issued and recorded do not relate to valid sales / shipments or because invoices are not recorded at all. | I83: RSKDRS1 - Risk of misstatement of Accounts receivable because invoices issued and recorded do not relate to valid sales / shipments or because invoices are not recorded at all. | J83: NIL | K83: SPRE1 - Validity of recorded sales transactions SPRE7 - Checking gate passes to ensure invoices are not fictitious | T83: =LEN(G83) -> 177
B84: Receivables | C84: Rights | D84: =LEFT(G84) -> R | E84: =IF(MID(G84,2,1)="R", "OK","CHECK") -> OK | F84: RRSKDRS3 - Risk of misstatement of Accounts receivable because receipts from customers is recorded more than once or are not recorded at all. | G84: =TRIM(F84) -> RRSKDRS3 - Risk of misstatement of Accounts receivable because receipts from customers is recorded more than once or are not recorded at all. | H84: =MID(G84,LEN(D84)+1,T84-LEN(D84)) -> RSKDRS3 - Risk of misstatement of Accounts receivable because receipts from customers is recorded more than once or are not recorded at all. | I84: RSKDRS3 - Risk of misstatement of Accounts receivable because receipts from customers is recorded more than once or are not recorded at all. | J84: CACB2 - Monthly bank reco testing CACB3 - Bank confirmation testing | K84: SPCB2 - Bank reconciliation checking SPCB3 - Bank confirmation testing SPDRS1 - Drs ageing SPDRS5 - Confirmation procedures as on BS date/subsequent testing. SPDRS6 - Confirmation procedures on other date/subsequent testing. SPDRS7 - Drs Turnover ratio checking | T84: =LEN(G84) -> 141
B85: Receivables | C85: Rights | D85: =LEFT(G85) -> R | E85: =IF(MID(G85,2,1)="R", "OK","CHECK") -> OK | F85: RRSKDRS5 - Risk of overstatement of bad debts because debtors are written off as bad without proper approvals | G85: =TRIM(F85) -> RRSKDRS5 - Risk of overstatement of bad debts because debtors are written off as bad without proper approvals | H85: =MID(G85,LEN(D85)+1,T85-LEN(D85)) -> RSKDRS5 - Risk of overstatement of bad debts because debtors are written off as bad without proper approvals | I85: RSKDRS5 - Risk of overstatement of bad debts because debtors are written off as bad without proper approvals | J85: CADRS3 - Approvals for writeoff of debts | K85: SPDRS3 - Approvals for writeoff of debts | T85: =LEN(G85) -> 109
B86: Receivables | C86: Valuation | D86: =LEFT(G86) -> V | E86: =IF(MID(G86,2,1)="R", "OK","CHECK") -> OK | F86: VRSKDRS2 - Risk of misstatement of Accounts receivable because of errors in the calculation of sales value on the invoice. | G86: =TRIM(F86) -> VRSKDRS2 - Risk of misstatement of Accounts receivable because of errors in the calculation of sales value on the invoice. | H86: =MID(G86,LEN(D86)+1,T86-LEN(D86)) -> RSKDRS2 - Risk of misstatement of Accounts receivable because of errors in the calculation of sales value on the invoice. | I86: RSKDRS2 - Risk of misstatement of Accounts receivable because of errors in the calculation of sales value on the invoice. | J86: CARE3 - Comparision with pricelists CARE4 - Checking invoice autocomputation CARE5 - Checking for unauthorised access | K86: SPRE3 - Checking pricelists and discounts | T86: =LEN(G86) -> 122
B87: Receivables | C87: Valuation | D87: =LEFT(G87) -> V | E87: =IF(MID(G87,2,1)="R", "OK","CHECK") -> OK | F87: VRSKDRS4 - Risk of overstatement of Accounts receivable because of understatement of allowance for doubtful debts. | G87: =TRIM(F87) -> VRSKDRS4 - Risk of overstatement of Accounts receivable because of understatement of allowance for doubtful debts. | H87: =MID(G87,LEN(D87)+1,T87-LEN(D87)) -> RSKDRS4 - Risk of overstatement of Accounts receivable because of understatement of allowance for doubtful debts. | I87: RSKDRS4 - Risk of overstatement of Accounts receivable because of understatement of allowance for doubtful debts. | J87: NIL | K87: SPDRS1 - Drs ageing SPDRS2 - Check debtors provisioning SPDRS4 - Reconcile ageing report with GL | T87: =LEN(G87) -> 114
B88: Receivables | C88: Valuation | D88: =LEFT(G88) -> V | E88: =IF(MID(G88,2,1)="R", "OK","CHECK") -> OK | F88: VRSKDRS3 - Risk of misstatement of Accounts receivable because receipts from customers is recorded more than once or are not recorded at all. | G88: =TRIM(F88) -> VRSKDRS3 - Risk of misstatement of Accounts receivable because receipts from customers is recorded more than once or are not recorded at all. | H88: =MID(G88,LEN(D88)+1,T88-LEN(D88)) -> RSKDRS3 - Risk of misstatement of Accounts receivable because receipts from customers is recorded more than once or are not recorded at all. | I88: RSKDRS3 - Risk of misstatement of Accounts receivable because receipts from customers is recorded more than once or are not recorded at all. | J88: CACB2 - Monthly bank reco testing CACB3 - Bank confirmation testing | K88: SPCB2 - Bank reconciliation checking SPCB3 - Bank confirmation testing SPDRS1 - Drs ageing SPDRS5 - Confirmation procedures as on BS date/subsequent testing. SPDRS6 - Confirmation procedures on other date/subsequent testing. SPDRS7 - Drs Turnover ratio checking | T88: =LEN(G88) -> 141
B89: Receivables | C89: Valuation | D89: =LEFT(G89) -> V | E89: =IF(MID(G89,2,1)="R", "OK","CHECK") -> OK | F89: VRSKDRS5 - Risk of overstatement of bad debts because debtors are written off as bad without proper approvals | G89: =TRIM(F89) -> VRSKDRS5 - Risk of overstatement of bad debts because debtors are written off as bad without proper approvals | H89: =MID(G89,LEN(D89)+1,T89-LEN(D89)) -> RSKDRS5 - Risk of overstatement of bad debts because debtors are written off as bad without proper approvals | I89: RSKDRS5 - Risk of overstatement of bad debts because debtors are written off as bad without proper approvals | J89: CADRS3 - Approvals for writeoff of debts | K89: SPDRS3 - Approvals for writeoff of debts | T89: =LEN(G89) -> 109
B90: Investments | C90: Allocation | D90: =LEFT(G90) -> A | E90: =IF(MID(G90,2,1)="R", "OK","CHECK") -> OK | F90: ARSKINMT2-Risk of misstatement of investments in shares and mutual funds since amounts invested are not accounted and measured as per the requirements of relevant accounting standards | G90: =TRIM(F90) -> ARSKINMT2-Risk of misstatement of investments in shares and mutual funds since amounts invested are not accounted and measured as per the requirements of relevant accounting standards | H90: =MID(G90,LEN(D90)+1,T90-LEN(D90)) -> RSKINMT2-Risk of misstatement of investments in shares and mutual funds since amounts invested are not accounted and measured as per the requirements of relevant accounting standards | I90: RSKINMT2-Risk of misstatement of investments in shares and mutual funds since amounts invested are not accounted and measured as per the requirements of relevant accounting standards | J90: NIL | K90: SPINMT3 - Comparison with statements and cost FMV comparison | T90: =LEN(G90) -> 183
B91: Investments | C91: Completeness | D91: =LEFT(G91) -> C | E91: =IF(MID(G91,2,1)="R", "OK","CHECK") -> OK | F91: CRSKINMT1-Risk of misstatement of investment in chit funds since payments to chit companies are not correctly accounted in the books of account | G91: =TRIM(F91) -> CRSKINMT1-Risk of misstatement of investment in chit funds since payments to chit companies are not correctly accounted in the books of account | H91: =MID(G91,LEN(D91)+1,T91-LEN(D91)) -> RSKINMT1-Risk of misstatement of investment in chit funds since payments to chit companies are not correctly accounted in the books of account | I91: RSKINMT1-Risk of misstatement of investment in chit funds since payments to chit companies are not correctly accounted in the books of account | J91: NIL | K91: SPINMT1 - Comparison of amounts booked with statements SPINMT2 - Comparison with confirmations | T91: =LEN(G91) -> 143
B92: Investments | C92: Existence | D92: =LEFT(G92) -> E | E92: =IF(MID(G92,2,1)="R", "OK","CHECK") -> OK | F92: ERSKINMT1-Risk of misstatement of investment in chit funds since payments to chit companies are not correctly accounted in the books of account | G92: =TRIM(F92) -> ERSKINMT1-Risk of misstatement of investment in chit funds since payments to chit companies are not correctly accounted in the books of account | H92: =MID(G92,LEN(D92)+1,T92-LEN(D92)) -> RSKINMT1-Risk of misstatement of investment in chit funds since payments to chit companies are not correctly accounted in the books of account | I92: RSKINMT1-Risk of misstatement of investment in chit funds since payments to chit companies are not correctly accounted in the books of account | J92: NIL | K92: SPINMT1 - Comparison of amounts booked with statements SPINMT2 - Comparison with confirmations | T92: =LEN(G92) -> 143
B93: Investments | C93: Existence | D93: =LEFT(G93) -> E | E93: =IF(MID(G93,2,1)="R", "OK","CHECK") -> OK | F93: ERSKINMT2-Risk of misstatement of investments in shares and mutual funds since amounts invested are not accounted and measured as per the requirements of relevant accounting standards | G93: =TRIM(F93) -> ERSKINMT2-Risk of misstatement of investments in shares and mutual funds since amounts invested are not accounted and measured as per the requirements of relevant accounting standards | H93: =MID(G93,LEN(D93)+1,T93-LEN(D93)) -> RSKINMT2-Risk of misstatement of investments in shares and mutual funds since amounts invested are not accounted and measured as per the requirements of relevant accounting standards | I93: RSKINMT2-Risk of misstatement of investments in shares and mutual funds since amounts invested are not accounted and measured as per the requirements of relevant accounting standards | J93: NIL | K93: SPINMT3 - Comparison with statements and cost FMV comparison | T93: =LEN(G93) -> 183
